Workbook

Sheet Requirements
A1: Participant ID | B1: Original Requirement | C1: Translation | D1: User Story | E1: Domain | H1: Task 1 | I1: Task 2 | J1: Task 3
A2: Participant A | B2: The application shall provide accurate classification results with a minimum accuracy of 90% for binary classification problems, as evaluated by metrics such as F1-score, Recall, Precision, Accuracy or Mean squared error. | C2: The application shall provide accurate classification results with a minimum accuracy of 90% for binary classification problems, as evaluated by metrics such as F1-score, Recall, Precision, Accuracy or Mean squared error. | D2: As a biologist, I want the application to provide accurate classification results with a minimum accuracy of 90% for binary classification problems, as evaluated by metrics such as F1-score, Recall, Precision, Accuracy or Mean squared error, so that I can trust the model's results and make informed decisions based on the predictions. | E2: Biology | F2: Biology | G2: =IF(F2=Requirements!E2,"true","") -> true | H2: classification | K2: classification
A3: Participant A | B3: The application shall provide continuous monitoring and evaluation of the machine learning model's performance and accuracy, with feedback loops to improve the model over time. | C3: The application shall provide continuous monitoring and evaluation of the machine learning model's performance and accuracy, with feedback loops to improve the model over time. | D3: As a biologist, I want the application to provide continuous monitoring and evaluation of the machine learning model's performance and accuracy, with feedback loops to improve the model over time, so that I can adapt the model to changing biological conditions and improve its performance over time. | E3: Biology | F3: Biology | G3: =IF(F3=Requirements!E3,"true","") -> true | H3: spatio-temporal process learning | K3: classification | L3: clustering | M3: entity resolution | N3: representation learning | O3: sentiment analysis
A4: Participant A | B4: The application shall use interpretability techniques such as feature importance scores, decision trees, or saliency maps to understand the underlying biological mechanisms and validate the model's predictions. This can help build trust in the model's results and provide insights into the biological mechanisms underlying cancer subtypes. Furthermore high-dimensional genomic data can lead to spurious correlations and false discoveries, and in these cases interpretability can also help identify and remove them by identifying the genes and pathways that are driving the classification results. | C4: The application shall use interpretability techniques such as feature importance scores, decision trees, or saliency maps to understand the underlying biological mechanisms and validate the model's predictions. This can help build trust in the model's results and provide insights into the biological mechanisms underlying cancer subtypes. Furthermore high-dimensional genomic data can lead to spurious correlations and false discoveries, and in these cases interpretability can also help identify and remove them by identifying the genes and pathways that are driving the classification results. | D4: As a biologist, I want the application to use interpretability techniques such as feature importance scores, decision trees, or saliency maps to understand the underlying biological mechanisms and validate the model's predictions, so that I can gain insights into the biological mechanisms underlying cancer subtypes and identify the genes and pathways driving the classification results. | E4: Biology | F4: Biology | G4: =IF(F4=Requirements!E4,"true","") -> true | H4: classification | K4: anomaly detection
A5: Participant A | B5: The application must access to large-scale genomic datasets such as The Cancer Genome Atlas (TCGA) or International Cancer Genome Consortium (ICGC) to get the data necessary to perform this task. | C5: The application must access to large-scale genomic datasets such as The Cancer Genome Atlas (TCGA) or International Cancer Genome Consortium (ICGC) to get the data necessary to perform this task. | D5: As a biologist, I want to access large-scale genomic datasets such as The Cancer Genome Atlas (TCGA) or International Cancer Genome Consortium (ICGC) to get the data necessary to perform this task, so that I can analyze a diverse range of cancer types and gain a comprehensive understanding of cancer biology. | E5: Biology | F5: Biology | G5: =IF(F5=Requirements!E5,"true","") -> true | H5: clustering | K5: anomaly detection | L5: bias detection in language models | M5: bias detection in word embeddings | N5: classification | O5: entity resolution | P5: regression | Q5: sentiment analysis
A6: Participant A | B6: The application shall leverage cloud-based computing platforms and big data analytics to handle the high dimensionality of omics data and achieve scalable and efficient classification and clustering. | C6: The application shall leverage cloud-based computing platforms and big data analytics to handle the high dimensionality of omics data and achieve scalable and efficient classification and clustering. | D6: As a biologist, I want to leverage cloud-based computing platforms and big data analytics to handle the high dimensionality of omics data and achieve scalable and efficient classification and clustering, so that I can analyze large-scale genomic datasets and gain insights into the mechanisms underlying cancer subtypes. | E6: Biology | F6: Biology | G6: =IF(F6=Requirements!E6,"true","") -> true | H6: classification | I6: clustering | K6: advertising | L6: anomaly detection | M6: bias detection in language models | N6: bias detection in word embeddings | O6: classification | P6: clustering | Q6: data summarization | R6: districting | S6: entity resolution | T6: graph augmentation | U6: graph diffusion | V6: graph mining | W6: machine translation | X6: matching | Y6: pricing | Z6: ranking | AA6: regression | AB6: representation learning | AC6: resource allocation | AD6: risk assessment | AE6: sentiment analysis | AF6: spatio-temporal process learning | AG6: speech recognition | AH6: subset selection | AI6: task assignment
A7: Participant A | B7: The application shall use data preparation techniques such as sampling, feature selection, data cleaning, parallel processing, and dimensionality reduction to be able to process large-scale omics data. | C7: The application shall use data preparation techniques such as sampling, feature selection, data cleaning, parallel processing, and dimensionality reduction to be able to process large-scale omics data. | D7: As a biologist, I want to use data preparation techniques such as sampling, feature selection, data cleaning, parallel processing, and dimensionality reduction to be able to process large-scale omics data, so that I can optimize the performance of the machine learning models and reduce the impact of noise and spurious correlations. | E7: Biology | F7: Biology | G7: =IF(F7=Requirements!E7,"true","") -> true | H7: subset selection | K7: anomaly detection | L7: classification | M7: ranking | N7: regression | O7: representation learning | P7: sentiment analysis
A8: Participant A | B8: The application shall use supervised classification algorithms such as random forest, logistic regression, or deep learning neural networks to classify cancer subtypes based on gene expression profiles. | C8: The application shall use supervised classification algorithms such as random forest, logistic regression, or deep learning neural networks to classify cancer subtypes based on gene expression profiles. | D8: As a biologist, I want to use supervised classification algorithms such as random forest, logistic regression, or deep learning neural networks to classify cancer subtypes based on gene expression profiles, so that I can accurately identify different cancer subtypes and potentially develop targeted therapies. | E8: Biology | F8: Biology | G8: =IF(F8=Requirements!E8,"true","") -> true | H8: classification | K8: classification
A9: Participant A | B9: The application shall use unsupervised clustering algorithms such as K-means, hierarchical clustering, or principal component analysis to identify molecular subtypes of cancer based on genomic data. | C9: The application shall use unsupervised clustering algorithms such as K-means, hierarchical clustering, or principal component analysis to identify molecular subtypes of cancer based on genomic data. | D9: As a biologist, I want to use unsupervised clustering algorithms such as K-means, hierarchical clustering, or principal component analysis to identify molecular subtypes of cancer based on genomic data, so that I can gain insights into the underlying biological mechanisms driving cancer subtypes. | E9: Biology | F9: Biology | G9: =IF(F9=Requirements!E9,"true","") -> true | H9: clustering | K9: anomaly detection | L9: clustering | M9: representation learning
A10: Participant B | B10: Il sistema deve utilizzare algoritmi di ML per l'apprendimento di processi spazio-temporali | C10: The system must use ML algorithms for learning spatio-temporal processes. | D10: As a cardiologist, I want it to use ML algorithms for learning spatio-temporal processes so that it can continuously improve its accuracy in detecting and diagnosing cardiac diseases. | E10: Cardiology | F10: Cardiology | G10: =IF(F10=Requirements!E10,"true","") -> true | H10: spatio-temporal process learning | K10: anomaly detection | L10: bias detection in language models | M10: bias detection in word embeddings | N10: classification | O10: representation learning | P10: sentiment analysis
A11: Participant B | B11: Il sistema deve individuare pattern che possono indicare la presenza di malattie cardiache nei segnali Echo | C11: The system must identify patterns in Echo signals that may indicate the presence of cardiac disease. | D11: As a cardiologist, I want the system to identify patterns in Echo signals that may indicate the presence of cardiac disease so that I can diagnose and treat patients accurately. | E11: Cardiology | F11: Cardiology | G11: =IF(F11=Requirements!E11,"true","") -> true | H11: anomaly detection | K11: anomaly detection | L11: classification | M11: data summarization
A12: Participant B | B12: Il sistema deve processare segnali ECG | C12: The system must process ECG signals. | D12: As a cardiologist, I want the system to process ECG signals so that I can analyze the electrical activity of a patient's heart and detect any abnormalities. | E12: Cardiology | F12: Cardiology | G12: =IF(F12=Requirements!E12,"true","") -> true | H12: anomaly detection | K12: advertising | L12: anomaly detection | M12: bias detection in language models | N12: bias detection in word embeddings | O12: classification | P12: clustering | Q12: data summarization | R12: districting | S12: entity resolution | T12: graph augmentation | U12: graph diffusion | V12: graph mining | W12: machine translation | X12: matching | Y12: pricing | Z12: ranking | AA12: regression | AB12: representation learning | AC12: resource allocation | AD12: risk assessment | AE12: sentiment analysis | AF12: spatio-temporal process learning | AG12: speech recognition | AH12: subset selection | AI12: task assignment
A13: Participant B | B13: Il sistema deve processare segnali Echo | C13: The system must process Echo signals. | D13: As a cardiologist, I want the system to process Echo signals so that I can analyze the structure and function of a patient's heart and detect any abnormalities. | E13: Cardiology | F13: Cardiology | G13: =IF(F13=Requirements!E13,"true","") -> true | H13: anomaly detection | K13: other
A14: Participant B | B14: Il sistema deve riconoscere anomalie nei segnali ECG | C14: The system must recognize anomalies in ECG signals. | D14: As a cardiologist, I want the system to recognize anomalies in ECG signals so that I can identify any irregularities in a patient's heart activity and determine the appropriate treatment. | E14: Cardiology | F14: Cardiology | G14: =IF(F14=Requirements!E14,"true","") -> true | H14: anomaly detection | K14: anomaly detection | L14: bias detection in language models | M14: bias detection in word embeddings | N14: classification | O14: clustering | P14: entity resolution | Q14: machine translation | R14: matching | S14: ranking | T14: regression | U14: representation learning | V14: sentiment analysis | W14: speech recognition
A15: Participant B | B15: Il sistema deve riconoscere anomalie nei segnali Echo | C15: The system must recognize anomalies in Echo signals. | D15: As a cardiologist, I want the system to recognize anomalies in Echo signals so that I can identify any irregularities in a patient's heart structure or function and determine the appropriate treatment. | E15: Cardiology | F15: Cardiology | G15: =IF(F15=Requirements!E15,"true","") -> true | H15: anomaly detection | K15: anomaly detection | L15: bias detection in language models | M15: bias detection in word embeddings | N15: classification | O15: clustering | P15: entity resolution | Q15: machine translation | R15: matching | S15: ranking | T15: regression | U15: representation learning | V15: sentiment analysis | W15: speech recognition
A16: Participant M | B16: Il sistema deve utilizzare un algoritmo di filtraggio collaborativo per selezionare i direttori del casting per specifiche attività di selezione del casting in base alle capacità, all’esperienza e alle preferenze. | C16: The system must use a collaborative filtering algorithm to select casting directors for specific casting selection activities based on their abilities, experience, and preferences. | D16: As a casting director, I want the system to recommend me for specific casting selection activities based on my abilities, experience, and preferences, so that I can increase my chances of being selected for projects that match my expertise. | E16: Movies | F16: Medicine | G16: =IF(F16=Requirements!E16,"true","") | H16: matching | I16: classification | J16: clustering | K16: ranking
A17: Participant M | B17: Il sistema deve utilizzare una tecnica di filtraggio basato sui contenuti per analizzare le caratteristiche degli attori e delle attrici e assegnargli specifici ruoli. | C17: The system must use a content-based filtering technique to analyze the characteristics of actors and actresses and assign them specific roles. | D17: As a casting director, I want the system to use a content-based filtering technique to analyze the characteristics of actors and actresses and assign them specific roles, so that I can ensure that the right candidates are selected for the right roles. | E17: Movies | F17: Biology | G17: =IF(F17=Requirements!E17,"true","") | H17: subset selection | K17: other
A18: Participant M | B18: Il sistema deve utilizzare degli algoritmi per la classificazione delle competenze di un attore al fine di comprendere similarità tra i candidati ed affinità con un determinato ruolo. | C18: The system must use algorithms for the classification of an actor's skills to understand similarities between candidates and affinity with a particular role. | D18: As a casting director, I want the system to use algorithms for the classification of an actor's skills to understand similarities between candidates and affinity with a particular role, so that I can make better casting decisions and increase the chances of producing successful films. | E18: Movies | F18: Medicine | G18: =IF(F18=Requirements!E18,"true","") | H18: classification | K18: other
A19: Participant M | B19: Il sistema deve utilizzare la tecnica di analisi semantica (Latent Semantic Analysis) sui copioni di tutti i ruoli per estrarre dati significativi, confrontarli con le caratteristiche degli attori e utilizzarli per selezionare attori e attrici con maggior tasso di compatibilità. | C19: The system must use the technique of semantic analysis (Latent Semantic Analysis) on the scripts of all roles to extract significant data, compare them with the characteristics of actors and use them to select actors and actresses with a higher compatibility rate. | D19: As a casting director, I want the system to use the technique of semantic analysis (Latent Semantic Analysis) on the scripts of all roles to extract significant data, compare them with the characteristics of actors, and recommend actors and actresses with a higher compatibility rate, so that I can reduce the time and effort required to find suitable candidates. | E19: Movies | F19: Biology | G19: =IF(F19=Requirements!E19,"true","") | H19: subset selection | K19: classification | L19: regression
A20: Participant S | B20: Come sistema, voglio implementare algoritmi di regressione supervisionati, come la regressione random forest o la regressione gradient boosting, in modo da prevedere il numero di punti o di gol che un giocatore probabilmente segnerà in una determinata partita o stagione, in base a una serie di caratteristiche di input (come l'età, il regime di allenamento, gli infortuni precedenti e le condizioni ambientali). | C20: As a system, I want to implement supervised regression algorithms, such as random forest regression or gradient boosting regression, in order to predict the number of points or goals a player is likely to score in a given game or season, based on a series of input features (such as age, training regime, past injuries, and environmental conditions). | D20: As a coach or team manager, I want the system to predict the number of points or goals a player is likely to score in a given game or season, based on a series of input features such as age, training regime, past injuries, and environmental conditions, so that I can develop game strategies and improve team performance. | E20: Sport | F20: News | G20: =IF(F20=Requirements!E20,"true","") | H20: regression | K20: anomaly detection | L20: bias detection in language models | M20: bias detection in word embeddings | N20: classification | O20: clustering | P20: data summarization | Q20: graph mining | R20: machine translation | S20: matching | T20: ranking | U20: sentiment analysis
A21: Participant R | B21: As an ML-intensive application, I want to utilize advanced supervised regression algorithms, such as random forest regression or gradient boosting regression, to accurately predict athlete performance in complex and dynamic team sports scenarios. | C21: As an ML-intensive application, I want to utilize advanced supervised regression algorithms, such as random forest regression or gradient boosting regression, to accurately predict athlete performance in complex and dynamic team sports scenarios. | D21: As a coach, I want to use advanced supervised regression algorithms to accurately predict the performance of my athletes in complex and dynamic team sports scenarios, such as soccer or basketball. | E21: Sport | F21: Sport | G21: =IF(F21=Requirements!E21,"true","") -> true | H21: regression | K21: classification
A22: Participant Q | B22: Post Bias Identification: The system must recognize through Natural Language Processing algorithms the potential post bias | C22: Post Bias Identification: The system must recognize through Natural Language Processing algorithms the potential post bias | D22: As a cognitive psychologist, I want the system to recognize potential post bias through Natural Language Processing algorithms so that I can understand the cognitive processes underlying the interpretation of biased information by individuals in my research on cognitive biases. | E22: Psychology | F22: Biology | G22: =IF(F22=Requirements!E22,"true","") | H22: bias detection in language models | K22: anomaly detection | L22: bias detection in language models | M22: bias detection in word embeddings | N22: clustering | O22: data summarization | P22: graph mining | Q22: representation learning | R22: sentiment analysis
A23: Participant E | B23: The system must be able to handle large amounts of data, with no limits on number of files, to ensure system scalability. | C23: The system must be able to handle large amounts of data, with no limits on number of files, to ensure system scalability. | D23: As a computer vision researcher, I want the system to be able to handle large amounts of data, with no limits on the number of files, so that I can process and analyze large datasets in computer vision research. | E23: Computer Vision | F23: Computer Vision | G23: =IF(F23=Requirements!E23,"true","") -> true | H23: graph mining | K23: anomaly detection | L23: bias detection in language models | M23: classification | N23: entity resolution | O23: machine translation | P23: regression | Q23: representation learning | R23: sentiment analysis | S23: speech recognition
A24: Participant S | B24: Come sistema, voglio essere in grado di normalizzare i dati di input in modo da ridurre la varianza e garantire che i valori di input siano comparabili. | C24: As a system, I want to be able to normalize input data in order to reduce variance and ensure that input values are comparable. | D24: As a data analyst or researcher in the sports domain, I want the system to be able to normalize input data, in order to reduce variance and ensure that input values are comparable, so that the model's predictions are more accurate. | E24: Sport | F24: Biology | G24: =IF(F24=Requirements!E24,"true","") | H24: regression | K24: classification
A25: Participant S | B25: Come sistema voglio poter utilizzare piattaforme di elaborazione basate su cloud e big data analytics in modo che il modello possa gestire grandi quantità di dati e ottenere regressioni e classifiche scalabili ed efficienti. | C25: As a system, I want to be able to use cloud-based processing platforms and big data analytics so that the model can handle large amounts of data and obtain scalable and efficient regressions and classifications. | D25: As a data analyst or researcher in the sports domain, I want the system to be able to use cloud-based processing platforms and big data analytics, so that the model can handle large amounts of sports data and obtain scalable and efficient regressions and classifications, for making timely and accurate predictions. | E25: Sport | F25: Sport | G25: =IF(F25=Requirements!E25,"true","") -> true | H25: regression | I25: classification | K25: other
A26: Participant I | B26: Il sistema deve essere in grado di fornire un'analisi dettagliata sulla diffusione dell'informazione all'interno della rete sociale. | C26: The system must be capable of providing a detailed analysis of information diffusion within the social network. | D26: As a data analyst, I want the system to provide a detailed analysis of information diffusion within the social network so that I can understand how users are interacting with the system. | E26: Information Systems | F26: Information Systems | G26: =IF(F26=Requirements!E26,"true","") -> true | H26: anomaly detection | K26: other
A27: Participant H | B27: The system shall identify and handle any outliers or extreme values in the data that may affect the accuracy of price predictions | C27: The system shall identify and handle any outliers or extreme values in the data that may affect the accuracy of price predictions | D27: As a data scientist in the finance industry, I want the system to identify and handle any outliers or extreme values in the data that may affect the accuracy of price predictions, so that I can ensure the accuracy of the predictions. | E27: Finance & Marketing | F27: Biology | G27: =IF(F27=Requirements!E27,"true","") | H27: anomaly detection | K27: speech recognition
A28: Participant I | B28: Il sistema deve essere in grado di personalizzare messaggi pubblicitari per i nodi più influenti della rete sociale. | C28: The system must be capable of personalizing advertising messages for the most influential nodes in the social network. | D28: As a digital marketer, I want the system to personalize advertising messages for the most influential nodes in the social network so that I can increase the effectiveness of my campaigns. | E28: Information Systems | F28: Computer Networks | G28: =IF(F28=Requirements!E28,"true","") | H28: advertising | K28: anomaly detection | L28: bias detection in language models | M28: bias detection in word embeddings | N28: classification | O28: clustering | P28: data summarization | Q28: graph mining | R28: machine translation | S28: matching | T28: ranking | U28: sentiment analysis
A29: Participant G | B29: As an investor investing in company shares, I want to extract that company's information, so that I can extract useful metrics that can be used in price prediction of that share. | C29: As an investor investing in company shares, I want to extract that company's information, so that I can extract useful metrics that can be used in price prediction of that share. | D29: As a finance investor, I want to access a company's financial information to extract useful metrics for price prediction of that share. | E29: Finance & Marketing | F29: Finance & Marketing | G29: =IF(F29=Requirements!E29,"true","") -> true | H29: pricing | K29: anomaly detection | L29: bias detection in language models | M29: bias detection in word embeddings | N29: classification | O29: clustering | P29: machine translation | Q29: ranking | R29: regression | S29: sentiment analysis | T29: speech recognition
A30: Participant G | B30: As an investor, I want to know when a certain asset I hold is predicted to lose value in the near feature, so that I can assess if to keep it or not. | C30: As an investor, I want to know when a certain asset I hold is predicted to lose value in the near feature, so that I can assess if to keep it or not. | D30: As a finance investor, I want to receive alerts when a certain asset I hold is predicted to lose value in the near future to make an informed decision about whether to hold or sell it. | E30: Finance & Marketing | F30: Finance & Marketing | G30: =IF(F30=Requirements!E30,"true","") -> true | H30: regression | K30: bias detection in language models | L30: bias detection in word embeddings | M30: classification | N30: entity resolution | O30: machine translation | P30: regression | Q30: sentiment analysis | R30: speech recognition
A31: Participant G | B31: As an investor, I want to know people's opinion/sentiment on a financial investment product, so that I can make predictions on the product's value. | C31: As an investor, I want to know people's opinion/sentiment on a financial investment product, so that I can make predictions on the product's value. | D31: As a finance investor, I want to see the sentiment/opinion of other investors on a financial investment product to make informed predictions about the product's value. | E31: Finance & Marketing | F31: Finance & Marketing | G31: =IF(F31=Requirements!E31,"true","") -> true | H31: sentiment analysis | K31: anomaly detection | L31: bias detection in language models | M31: bias detection in word embeddings | N31: classification | O31: clustering | P31: data summarization | Q31: graph mining | R31: machine translation | S31: matching | T31: ranking | U31: sentiment analysis
A32: Participant J | B32: Classificazione dei documenti legali: il sistema deve essere in grado di classificare diversi tipi di documenti legali, come contratti, azioni legali, sentenze, tra gli altri, per facilitarne la gestione e la ricerca. | C32: Classification of legal documents: The system must be able to classify different types of legal documents, such as contracts, legal actions, judgments, among others, to facilitate their management and retrieval. | D32: As a law firm administrator, I want the system to classify different types of legal documents so that I can easily manage and retrieve them. | E32: Law | F32: Law | G32: =IF(F32=Requirements!E32,"true","") -> true | H32: classification | K32: anomaly detection | L32: bias detection in language models | M32: bias detection in word embeddings | N32: classification | O32: machine translation | P32: matching | Q32: ranking | R32: regression | S32: representation learning | T32: sentiment analysis | U32: speech recognition
A33: Participant J | B33: Riepilogo automatico dei documenti legali: il sistema deve essere in grado di generare riepiloghi accurati e concisi dei documenti legali, che consentano agli utenti di comprenderne rapidamente il contenuto. | C33: Automatic summarization of legal documents: The system must be able to generate accurate and concise summaries of legal documents, allowing users to quickly understand their content. | D33: As a law student, I want the system to generate accurate and concise summaries of legal documents so that I can quickly understand their content. | E33: Law | F33: Law | G33: =IF(F33=Requirements!E33,"true","") -> true | H33: data summarization | K33: data summarization
A34: Participant J | B34: Consulenza legale automatizzata: il sistema deve essere in grado di fornire raccomandazioni legali automatizzate, basate sull'interpretazione dei testi giuridici e della giurisprudenza esistente. | C34: Automated legal advice: The system must be able to provide automated legal recommendations based on the interpretation of legal texts and existing case law. | D34: As a legal advisor, I want the system to provide automated legal recommendations based on the interpretation of legal texts and existing case law so that I can provide timely and accurate legal advice to clients. | E34: Law | F34: Law | G34: =IF(F34=Requirements!E34,"true","") -> true | H34: representation learning | K34: anomaly detection | L34: bias detection in language models | M34: classification | N34: clustering | O34: data summarization | P34: graph augmentation | Q34: graph diffusion | R34: graph mining | S34: machine translation | T34: matching | U34: ranking | V34: representation learning | W34: sentiment analysis | X34: speech recognition | Y34: subset selection
A35: Participant K | B35: The system shall use sentiment analysis and representation learning techniques to identify and extract legal arguments and reasoning expressed in legal documents, enabling legal professionals to better understand the legal reasoning involved in specific cases or issues. | C35: The system shall use sentiment analysis and representation learning techniques to identify and extract legal arguments and reasoning expressed in legal documents, enabling legal professionals to better understand the legal reasoning involved in specific cases or issues. | D35: As a legal analyst, I want the system to identify and extract legal arguments and reasoning expressed in legal documents so that I can better understand the legal reasoning involved in specific cases or issues. | E35: Law | F35: Law | G35: =IF(F35=Requirements!E35,"true","") -> true | H35: representation learning | K35: bias detection in language models | L35: data summarization | M35: entity resolution | N35: graph mining | O35: machine translation | P35: sentiment analysis | Q35: speech recognition
A36: Participant J | B36: Analisi del sentiment: il sistema deve essere in grado di analizzare il tono e l'atteggiamento dei testi legali per determinare se si tratta di un documento positivo, negativo o neutro. | C36: Sentiment analysis: The system must be able to analyze the tone and attitude of legal texts to determine if the document is positive, negative, or neutral. | D36: As a legal analyst, I want the system to perform sentiment analysis on legal texts so that I can understand the tone and attitude of legal documents. | E36: Law | F36: Law | G36: =IF(F36=Requirements!E36,"true","") -> true | H36: sentiment analysis | K36: machine translation | L36: speech recognition
A37: Participant K | B37: The system shall use supervised representation learning techniques to create document embeddings that can capture the similarities and differences between legal documents on specific legal topics, in order to provide legal professionals with an overview of similar cases. | C37: The system shall use supervised representation learning techniques to create document embeddings that can capture the similarities and differences between legal documents on specific legal topics, in order to provide legal professionals with an overview of similar cases. | D37: As a legal expert, I want the system to create document embeddings that can capture the similarities and differences between legal documents on specific legal topics so that I can better understand similar cases. | E37: Law | F37: Law | G37: =IF(F37=Requirements!E37,"true","") -> true | H37: representation learning | K37: anomaly detection | L37: classification | M37: regression | N37: sentiment analysis | O37: speech recognition
A38: Participant J | B38: Identificazione di problemi legali: il sistema deve essere in grado di identificare problemi legali nei testi, come ambiguità, contraddizioni o mancanza di coerenza. | C38: Identification of legal issues: The system must be able to identify legal issues in texts, such as ambiguity, contradictions, or lack of coherence. | D38: As a legal expert, I want the system to identify legal issues in texts, such as ambiguity or contradictions, so that I can ensure the accuracy and coherence of legal documents. | E38: Law | F38: Law | G38: =IF(F38=Requirements!E38,"true","") -> true | H38: anomaly detection | K38: anomaly detection | L38: bias detection in language models | M38: bias detection in word embeddings | N38: classification | O38: clustering | P38: data summarization | Q38: graph mining | R38: machine translation | S38: matching | T38: ranking | U38: regression | V38: representation learning | W38: sentiment analysis | X38: speech recognition | Y38: subset selection
A39: Participant K | B39: The system shall use NLP and representation learning techniques to “neutralize” the sentiment of a legal document while preserving its meaning, in order to help legal professionals create neutral documents as part of creating document embeddings for downstream tasks. | C39: The system shall use NLP and representation learning techniques to “neutralize” the sentiment of a legal document while preserving its meaning, in order to help legal professionals create neutral documents as part of creating document embeddings for downstream tasks. | D39: As a legal professional, I want the system to "neutralize" the sentiment of a legal document while preserving its meaning so that I can create neutral documents for downstream tasks. | E39: Law | F39: Law | G39: =IF(F39=Requirements!E39,"true","") -> true | H39: sentiment analysis | K39: anomaly detection | L39: clustering | M39: representation learning
A40: Participant J | B40: Rilevamento del plagio nei documenti legali: il sistema deve essere in grado di rilevare il plagio nei testi legali, identificando somiglianze e coincidenze con altri documenti legali esistenti. | C40: Detection of plagiarism in legal documents: The system must be able to detect plagiarism in legal texts, identifying similarities and coincidences with other existing legal documents. | D40: As a legal professional, I want the system to detect plagiarism in legal texts, identifying similarities and coincidences with other existing legal documents, so that I can ensure the originality of legal documents. | E40: Law | F40: Law | G40: =IF(F40=Requirements!E40,"true","") -> true | H40: matching | K40: anomaly detection
A41: Participant K | B41: The system shall be able to handle unstructured legal text data cases, law, contracts, and legislative documents in order to provide accurate sentiment analysis and representation learning results. | C41: The system shall be able to handle unstructured legal text data cases, law, contracts, and legislative documents in order to provide accurate sentiment analysis and representation learning results. | D41: As a legal professional, I want the system to handle unstructured legal text data, such as cases, laws, contracts, and legislative documents, so that I can get accurate sentiment analysis and representation learning results. | E41: Law | F41: Law | G41: =IF(F41=Requirements!E41,"true","") -> true | H41: sentiment analysis | I41: data summarization | K41: other
A42: Participant K | B42: The system shall use NLP techniques to perform sentiment analysis on legal documents and opinions related to specific issues, in order to help the identification of emotions and opinions. | C42: The system shall use NLP techniques to perform sentiment analysis on legal documents and opinions related to specific issues, in order to help the identification of emotions and opinions. | D42: As a legal professional, I want the system to perform sentiment analysis on legal documents and opinions related to specific issues so that I can identify the emotions and opinions expressed in the text. | E42: Law | F42: Law | G42: =IF(F42=Requirements!E42,"true","") -> true | H42: sentiment analysis | K42: sentiment analysis
A43: Participant K | B43: The system shall provide insights into the attitudes and emotions surrounding specific legal issues, to enable more informed decision-making and better case preparation. | C43: The system shall provide insights into the attitudes and emotions surrounding specific legal issues, to enable more informed decision-making and better case preparation. | D43: As a legal professional, I want the system to provide insights into the attitudes and emotions surrounding specific legal issues so that I can make more informed decisions and prepare for cases better. | E43: Law | F43: Law | G43: =IF(F43=Requirements!E43,"true","") -> true | H43: sentiment analysis | K43: data summarization | L43: entity resolution | M43: graph mining
A44: Participant K | B44: The system shall use representation learning techniques, in order to create efficient and effective document embeddings for downstream tasks. | C44: The system shall use representation learning techniques, in order to create efficient and effective document embeddings for downstream tasks. | D44: As a legal researcher, I want the system to create efficient and effective document embeddings for downstream tasks using representation learning techniques. | E44: Law | F44: Law | G44: =IF(F44=Requirements!E44,"true","") -> true | H44: representation learning | K44: other
A45: Participant J | B45: Estrazione automatica di informazioni rilevanti da testi legali: il sistema deve essere in grado di identificare ed estrarre informazioni chiave da testi legali, come nomi di persone, date, luoghi, termini legali specifici, tra gli altri. | C45: Automatic extraction of relevant information from legal texts: The system must be able to identify and extract key information from legal texts, such as names of people, dates, locations, specific legal terms, among others. | D45: As a legal researcher, I want the system to extract relevant information from legal texts so that I can quickly find the information I need for my research. | E45: Law | F45: Law | G45: =IF(F45=Requirements!E45,"true","") -> true | H45: data summarization | K45: advertising | L45: anomaly detection | M45: bias detection in language models | N45: bias detection in word embeddings | O45: classification | P45: clustering | Q45: data summarization | R45: districting | S45: entity resolution | T45: graph augmentation | U45: graph diffusion | V45: graph mining | W45: machine translation | X45: matching | Y45: pricing | Z45: ranking | AA45: regression | AB45: representation learning | AC45: resource allocation | AD45: risk assessment | AE45: sentiment analysis | AF45: spatio-temporal process learning | AG45: speech recognition | AH45: subset selection | AI45: task assignment
A46: Participant J | B46: Identificazione di somiglianze e differenze tra documenti legali: il sistema deve essere in grado di identificare somiglianze e differenze tra diversi documenti legali, che consentiranno agli utenti di confrontare e contrapporre diversi casi e sentenze. | C46: Identification of similarities and differences between legal documents: The system must be able to identify similarities and differences between different legal documents, allowing users to compare and contrast different cases and judgments. | D46: As a legal researcher, I want the system to identify similarities and differences between different legal documents so that I can compare and contrast different cases and judgments. | E46: Law | F46: Law | G46: =IF(F46=Requirements!E46,"true","") -> true | H46: matching | K46: anomaly detection | L46: bias detection in language models | M46: bias detection in word embeddings | N46: clustering | O46: data summarization | P46: entity resolution | Q46: representation learning | R46: subset selection
A47: Participant K | B47: The system shall use NLP techniques to perform speakers attribution and sentiment analysis for each speaker on case documents, in order to help legal professionals understand the emotions of all participants. | C47: The system shall use NLP techniques to perform speakers attribution and sentiment analysis for each speaker on case documents, in order to help legal professionals understand the emotions of all participants. | D47: As a legal researcher, I want the system to perform speaker attribution and sentiment analysis for each speaker on case documents so that I can understand the emotions of all participants. | E47: Law | F47: Law | G47: =IF(F47=Requirements!E47,"true","") -> true | H47: sentiment analysis | K47: other
A48: Participant J | B48: Analisi del rischio legale: il sistema deve essere in grado di analizzare i rischi legali associati a un contratto o accordo, identificando possibili lacune legali e potenziali rischi. | C48: Analysis of legal risk: The system must be able to analyze legal risks associated with a contract or agreement, identifying possible legal gaps and potential risks. | D48: As a legal risk manager, I want the system to analyze legal risks associated with a contract or agreement, identifying possible legal gaps and potential risks, so that I can mitigate legal risks for the organization. | E48: Law | F48: Law | G48: =IF(F48=Requirements!E48,"true","") -> true | H48: bias detection in language models | I48: bias detection in word embeddings | K48: anomaly detection | L48: classification | M48: clustering | N48: entity resolution | O48: graph mining | P48: regression | Q48: representation learning | R48: sentiment analysis | S48: subset selection
A49: Participant J | B49: Traduzione automatica di testi legali: il sistema deve essere in grado di tradurre automaticamente testi legali da una lingua all'altra, mantenendo l'accuratezza e la coerenza della lingua legale. | C49: Automatic translation of legal texts: The system must be able to automatically translate legal texts from one language to another while maintaining the accuracy and coherence of the legal language. | D49: As a legal translator, I want the system to automatically translate legal texts from one language to another while maintaining the accuracy and coherence of the legal language. | E49: Law | F49: Law | G49: =IF(F49=Requirements!E49,"true","") -> true | H49: machine translation | K49: speech recognition
A50: Participant L | B50: Traduzione di un libro o un articolo in un'altra lingua | C50: Translation of a book or article into another language | D50: As a literary researcher, I want to be able to translate a book or article into another language in the system so that I can study it in my preferred language. | E50: Literature | F50: Literature | G50: =IF(F50=Requirements!E50,"true","") | H50: machine translation | K50: anomaly detection | L50: bias detection in language models | M50: bias detection in word embeddings | N50: classification | O50: clustering | P50: data summarization | Q50: graph mining | R50: machine translation | S50: matching | T50: ranking | U50: sentiment analysis
A51: Participant L | B51: Sintesi del testo di un libro o di un articolo | C51: Summary of the text of a book or article | D51: As a literary researcher, I want to be able to view a summary of the content of a book or article in the system so that I can quickly understand its topic. | E51: Literature | F51: Literature | G51: =IF(F51=Requirements!E51,"true","") | H51: data summarization | K51: anomaly detection | L51: bias detection in language models | M51: bias detection in word embeddings | N51: classification | O51: clustering | P51: data summarization | Q51: graph mining | R51: machine translation | S51: matching | T51: ranking | U51: sentiment analysis
A52: Participant E | B52: The system must automatically detect any errors or problems in the processing and report them. | C52: The system must automatically detect any errors or problems in the processing and report them. | D52: As a machine learning engineer, I want the system to automatically detect any errors or problems in the processing and report them, so that I can improve the accuracy and performance of the computer vision algorithms. | E52: Computer Vision | F52: Computer Networks | G52: =IF(F52=Requirements!E52,"true","") | H52: entity resolution | I52: anomaly detection | K52: advertising | L52: anomaly detection | M52: bias detection in language models | N52: bias detection in word embeddings | O52: classification | P52: clustering | Q52: data summarization | R52: districting | S52: entity resolution | T52: graph augmentation | U52: graph diffusion | V52: graph mining | W52: machine translation | X52: matching | Y52: pricing | Z52: ranking | AA52: regression | AB52: representation learning | AC52: resource allocation | AD52: risk assessment | AE52: sentiment analysis | AF52: spatio-temporal process learning | AG52: speech recognition | AH52: subset selection | AI52: task assignment
A53: Participant N | B53: As a user of the machine learning system, I want the system to tune the hyperparameters of the machine learning algorithms used for clustering and summarization tasks, so that I can achieve better performance on my dataset. | C53: As a user of the machine learning system, I want the system to tune the hyperparameters of the machine learning algorithms used for clustering and summarization tasks, so that I can achieve better performance on my dataset. | D53: As a machine learning engineer, I want the system to optimize the hyperparameters of the machine learning algorithms used for clustering and summarization tasks, ensuring that the system achieves the best performance possible for my news data. | E53: News | F53: Biology | G53: =IF(F53=Requirements!E53,"true","") | H53: clustering | I53: data summarization | K53: anomaly detection | L53: bias detection in language models | M53: bias detection in word embeddings | N53: clustering | O53: data summarization | P53: entity resolution | Q53: graph augmentation | R53: graph diffusion | S53: graph mining | T53: matching | U53: ranking | V53: representation learning | W53: subset selection
A54: Participant N | B54: As a user of the machine learning system, I want the system to evaluate the performance of different machine learning algorithms and techniques for clustering and summarization tasks, so that I can choose the algorithm or technique that performs best on my dataset. | C54: As a user of the machine learning system, I want the system to evaluate the performance of different machine learning algorithms and techniques for clustering and summarization tasks, so that I can choose the algorithm or technique that performs best on my dataset. | D54: As a machine learning practitioner, I want the system to evaluate and compare the performance of different clustering and summarization algorithms, so that I can select the best algorithm for my specific news data and analytical needs. | E54: News | F54: Biology | G54: =IF(F54=Requirements!E54,"true","") | H54: clustering | I54: data summarization | K54: anomaly detection | L54: classification | M54: data summarization | N54: regression
A55: Participant I | B55: Il sistema deve essere in grado di integrare tecniche di apprendimento automatico per migliorare la qualità dell'analisi della diffusione grafica. | C55: The system must be capable of integrating machine learning techniques to improve the quality of the graph diffusion analysis. | D55: As a machine learning specialist, I want the system to integrate machine learning techniques to improve the quality of the graph diffusion analysis so that I can make more accurate predictions about user behavior. | E55: Information Systems | F55: Biology | G55: =IF(F55=Requirements!E55,"true","") | H55: graph diffusion | K55: other
A56: Participant I | B56: Il sistema deve essere in grado di identificare i nodi più influenti nella rete sociale sulla base di tecniche di diffusione grafica. | C56: The system must be capable of identifying the most influential nodes in the social network based on graph diffusion techniques. | D56: As a marketing manager, I want the system to identify the most influential nodes in the social network using graph diffusion techniques so that I can create targeted advertising campaigns. | E56: Information Systems | F56: Finance & Marketing | G56: =IF(F56=Requirements!E56,"true","") | H56: graph diffusion | K56: anomaly detection | L56: clustering | M56: districting | N56: graph augmentation | O56: graph diffusion | P56: representation learning | Q56: resource allocation | R56: subset selection
A57: Participant C | B57: Il modello deve utilizzare algoritmi di apprendimento per rinforzo per adattarsi dinamicamente alle mutevoli esigenze della rete. | C57: The system must use reinforcement learning algorithms to adapt dynamically to changing network needs. | D57: As a network administrator, I want the system to adapt dynamically to changing network needs using reinforcement learning algorithms, so that the network can respond to changing conditions and maintain optimal performance. | E57: Computer Networks | F57: Computer Networks | G57: =IF(F57=Requirements!E57,"true","") -> true | H57: Other | K57: anomaly detection | L57: bias detection in language models | M57: bias detection in word embeddings | N57: classification | O57: representation learning | P57: sentiment analysis
A58: Participant D | B58: The system must attach more resources (if free) to an application if it's recognized that more resources are needed to fulfill its tasks. | C58: The system must attach more resources (if free) to an application if it's recognized that more resources are needed to fulfill its tasks. | D58: As a network administrator, I want the system to automatically attach more resources to an application if it's recognized that more resources are needed to fulfill its tasks, so that applications can run efficiently. | E58: Computer Networks | F58: Computer Networks | G58: =IF(F58=Requirements!E58,"true","") -> true | H58: graph augmentation | K58: classification | L58: clustering | M58: regression | N58: representation learning | O58: sentiment analysis
A59: Participant D | B59: The system must detach resources to an application if it recognizes that too many resources are attached to it but aren't used. | C59: The system must detach resources to an application if it recognizes that too many resources are attached to it but aren't used. | D59: As a network administrator, I want the system to automatically detach resources from an application if it's recognized that too many resources are attached to it but aren't being used, so that resources can be used efficiently. | E59: Computer Networks | F59: Computer Networks | G59: =IF(F59=Requirements!E59,"true","") -> true | H59: graph augmentation | K59: anomaly detection | L59: bias detection in language models | M59: bias detection in word embeddings | N59: classification | O59: representation learning | P59: sentiment analysis
A60: Participant C | B60: Il sistema dovrebbe utilizzare algoritmi di classificazione per classificare i pacchetti di dati in base alle priorità e indirizzarli in modo appropriato per evitare la congestione di rete. | C60: The system should use classification algorithms to categorize data packets based on priority and route them appropriately to avoid network congestion. | D60: As a network administrator, I want the system to categorize data packets based on priority using classification algorithms and route them appropriately to avoid network congestion, so that high-priority data can be processed first and network performance can be maintained. | E60: Computer Networks | F60: Computer Networks | G60: =IF(F60=Requirements!E60,"true","") -> true | H60: classification | K60: regression
A61: Participant C | B61: Il sistema deve utilizzare algoritmi di classificazione in modo da distinguere trasmissioni di dati regolari e trasmissioni di dati anomali per la predizione di eventuali guasti e risolverli prima che si verifichino. | C61: The system must use classification algorithms to distinguish between regular and anomalous data transmissions for predicting and resolving potential failures before they occur. | D61: As a network administrator, I want the system to distinguish between regular and anomalous data transmissions using classification algorithms, so that potential failures can be predicted and resolved before they occur, and network security can be maintained. | E61: Computer Networks | F61: Computer Networks | G61: =IF(F61=Requirements!E61,"true","") -> true | H61: classification | I61: anomaly detection | K61: anomaly detection | L61: bias detection in language models | M61: bias detection in word embeddings | N61: classification | O61: representation learning | P61: sentiment analysis
A62: Participant C | B62: Il sistema deve utilizzare algoritmi di allocazione delle risorse, come l'apprendimento per rinforzo o gli algoritmi genetici, per allocare dinamicamente le risorse in base alla topologia della rete, ai modelli di traffico e ai requisiti di prestazione. | C62: The system must use resource allocation algorithms, such as reinforcement learning or genetic algorithms, to dynamically allocate resources based on network topology, traffic patterns, and performance requirements. | D62: As a network administrator, I want the system to dynamically allocate resources using reinforcement learning or genetic algorithms, based on network topology, traffic patterns, and performance requirements, so that the network can be optimized for efficiency and scalability. | E62: Computer Networks | F62: Computer Networks | G62: =IF(F62=Requirements!E62,"true","") -> true | H62: resource allocation | K62: anomaly detection | L62: bias detection in language models | M62: bias detection in word embeddings | N62: classification | O62: entity resolution | P62: graph augmentation | Q62: graph diffusion | R62: machine translation | S62: matching | T62: ranking | U62: regression | V62: representation learning | W62: risk assessment | X62: sentiment analysis | Y62: spatio-temporal process learning | Z62: speech recognition | AA62: task assignment
A63: Participant C | B63: Il sistema deve utilizzare tecniche per la gestione del traffico in modo efficiente per ridurre o aumentare il numero di nodi in base all’affluenza dei dati in tempo reale. | C63: The system must use techniques for managing traffic efficiently to reduce or increase the number of nodes based on real-time data flow. | D63: As a network administrator, I want the system to manage traffic efficiently using real-time data flow, so that the number of nodes can be dynamically reduced or increased based on network traffic. | E63: Computer Networks | F63: Computer Networks | G63: =IF(F63=Requirements!E63,"true","") -> true | H63: graph augmentation | K63: anomaly detection | L63: bias detection in language models | M63: classification | N63: entity resolution | O63: machine translation | P63: regression | Q63: representation learning | R63: sentiment analysis | S63: speech recognition
A64: Participant C | B64: Il sistema deve sfruttare algoritmi di clustering di attività per monitorare la topologia delle reti di computer e identificare potenziali attività insolite. | C64: The system must use clustering algorithms to monitor computer network topology and identify potential unusual activity. | D64: As a network administrator, I want the system to monitor the network topology and identify unusual activity using clustering algorithms, so that I can take necessary actions to prevent network security breaches. | E64: Computer Networks | F64: Computer Networks | G64: =IF(F64=Requirements!E64,"true","") -> true | H64: clustering | K64: classification
A65: Participant D | B65: The system must recognize if an application is given too few resources in order to serve its purpose. | C65: The system must recognize if an application is given too few resources in order to serve its purpose. | D65: As a network administrator, I want the system to recognize if an application is given too few resources to serve its purpose, so that I can allocate additional resources as needed. | E65: Computer Networks | F65: Computer Networks | G65: =IF(F65=Requirements!E65,"true","") -> true | H65: resource allocation | K65: anomaly detection | L65: bias detection in language models | M65: bias detection in word embeddings | N65: classification | O65: entity resolution | P65: regression | Q65: sentiment analysis
A66: Participant C | B66: Il sistema deve utilizzare algoritmi di incremento del grafo per aggiornare la topologia della rete con nodi e bordi aggiuntivi per catturare le relazioni tra dispositivi e applicazioni. | C66: The system must use graph incrementing algorithms to update the network topology with additional nodes and edges to capture relationships between devices and applications. | D66: As a network administrator, I want the system to update the network topology with additional nodes and edges using graph incrementing algorithms, so that I can capture relationships between devices and applications and maintain an up-to-date network topology. | E66: Computer Networks | F66: Computer Networks | G66: =IF(F66=Requirements!E66,"true","") -> true | H66: graph augmentation | K66: anomaly detection | L66: entity resolution | M66: matching | N66: sentiment analysis
A67: Participant C | B67: Il sistema dovrebbe sfruttare piattaforme informatiche basate su cloud e big data analytics per gestire i grandi volumi di dati sul traffico di rete e ottenere un aumento scalabile ed efficiente dei grafi. | C67: The system should use cloud-based computing platforms and big data analytics to manage large volumes of network traffic data and achieve scalable and efficient graph processing. | D67: As a network administrator, I want the system to use cloud-based computing platforms and big data analytics to manage large volumes of network traffic data and achieve scalable and efficient graph processing, so that network performance can be maintained even under heavy loads. | E67: Computer Networks | F67: Computer Networks | G67: =IF(F67=Requirements!E67,"true","") -> true | H67: graph mining | K67: anomaly detection | L67: bias detection in language models | M67: bias detection in word embeddings | N67: classification | O67: machine translation | P67: matching | Q67: ranking | R67: regression | S67: representation learning | T67: sentiment analysis | U67: speech recognition
A68: Participant D | B68: The system must (de)allocate resources for the running of the available applications in the network. | C68: The system must (de)allocate resources for the running of the available applications in the network. | D68: As a network administrator, I want to be able to allocate and deallocate resources for the running of available applications on the network, so that I can ensure that resources are used efficiently. | E68: Computer Networks | F68: Computer Networks | G68: =IF(F68=Requirements!E68,"true","") -> true | H68: graph augmentation | K68: anomaly detection | L68: classification | M68: regression | N68: sentiment analysis | O68: speech recognition
A69: Participant D | B69: The system must maintain updated a graph that represents all connections between applications and devices. | C69: The system must maintain updated a graph that represents all connections between applications and devices. | D69: As a network administrator, I want to be able to view an updated graph that represents all connections between applications and devices, so that I can easily track the network topology. | E69: Computer Networks | F69: Computer Networks | G69: =IF(F69=Requirements!E69,"true","") -> true | H69: graph augmentation | K69: anomaly detection | L69: bias detection in language models | M69: bias detection in word embeddings | N69: classification | O69: machine translation | P69: matching | Q69: ranking | R69: regression | S69: representation learning | T69: sentiment analysis | U69: speech recognition
A70: Participant N | B70: As a user of the machine learning system, I want the system to extract relevant features from the news articles, such as keywords and entities, for clustering and summarization tasks, so that I can use these features to group similar articles together based on their content. | C70: As a user of the machine learning system, I want the system to extract relevant features from the news articles, such as keywords and entities, for clustering and summarization tasks, so that I can use these features to group similar articles together based on their content. | D70: As a news analyst, I want the machine learning system to extract key entities and keywords from news articles to help me cluster and summarize similar articles based on their content. | E70: News | F70: News | G70: =IF(F70=Requirements!E70,"true","") -> true | H70: entity resolution | K70: anomaly detection | L70: bias detection in language models | M70: bias detection in word embeddings | N70: clustering | O70: data summarization | P70: entity resolution | Q70: graph augmentation | R70: graph diffusion | S70: graph mining | T70: matching | U70: ranking | V70: representation learning | W70: subset selection
A71: Participant N | B71: As a user of the machine learning system, I want the system to be able to handle news articles in multiple languages, so that I can analyze news from different regions of the world. | C71: As a user of the machine learning system, I want the system to be able to handle news articles in multiple languages, so that I can analyze news from different regions of the world. | D71: As a news correspondent, I want the machine learning system to be able to handle news articles in multiple languages, so that I can analyze news from various regions of the world and gain a broader perspective on global events. | E71: News | F71: News | G71: =IF(F71=Requirements!E71,"true","") -> true | H71: machine translation | K71: entity resolution
A72: Participant N | B72: As a user of the machine learning system, I want the system to preprocess and clean the data to remove noise, irrelevant information, and duplicates, so that I can work with high-quality data that is free from noise and redundancy. | C72: As a user of the machine learning system, I want the system to preprocess and clean the data to remove noise, irrelevant information, and duplicates, so that I can work with high-quality data that is free from noise and redundancy. | D72: As a news editor, I want the machine learning system to preprocess and clean news data to remove noise, irrelevant information, and duplicates, ensuring that the data is of high quality and free from redundancy. | E72: News | F72: News | G72: =IF(F72=Requirements!E72,"true","") -> true | H72: bias detection in language models | I72: bias detection in word embeddings | K72: advertising | L72: anomaly detection | M72: bias detection in language models | N72: bias detection in word embeddings | O72: classification | P72: clustering | Q72: data summarization | R72: districting | S72: entity resolution | T72: graph augmentation | U72: graph diffusion | V72: graph mining | W72: machine translation | X72: matching | Y72: pricing | Z72: ranking | AA72: regression | AB72: representation learning | AC72: resource allocation | AD72: risk assessment | AE72: sentiment analysis | AF72: spatio-temporal process learning | AG72: speech recognition | AH72: subset selection | AI72: task assignment
A73: Participant N | B73: As a user of the machine learning system, I want the system to be able to adapt to changes in the news domain, so that it can continue to provide relevant and informative summaries of news articles regardless of their topic. | C73: As a user of the machine learning system, I want the system to be able to adapt to changes in the news domain, so that it can continue to provide relevant and informative summaries of news articles regardless of their topic. | D73: As a news professional, I want the machine learning system to be adaptable and flexible enough to handle changes in the news domain, enabling it to provide relevant and informative summaries of news articles regardless of their topic. | E73: News | F73: News | G73: =IF(F73=Requirements!E73,"true","") -> true | H73: data summarization | K73: data summarization
A74: Participant N | B74: As a user of the machine learning system, I want the system to use different clustering techniques such as K-means and Hierarchical clustering to group similar articles together based on their content,so that I can choose the clustering technique that best fits my needs. | C74: As a user of the machine learning system, I want the system to use different clustering techniques such as K-means and Hierarchical clustering to group similar articles together based on their content,so that I can choose the clustering technique that best fits my needs. | D74: As a news publisher, I want the machine learning system to use a range of clustering techniques, such as K-means and Hierarchical clustering, to group similar news articles together based on their content, allowing me to efficiently categorize and organize news content for publishing. | E74: News | F74: News | G74: =IF(F74=Requirements!E74,"true","") -> true | H74: clustering | K74: other
A75: Participant N | B75: As a user of the machine learning system, I want the system to use different summarization techniques such as TextRank, LSA-based summarization, and other techniques, to generate concise yet informative summaries of the clustered groups, so that I can generate summaries of the grouped articles that are both concise and informative. | C75: As a user of the machine learning system, I want the system to use different summarization techniques such as TextRank, LSA-based summarization, and other techniques, to generate concise yet informative summaries of the clustered groups, so that I can generate summaries of the grouped articles that are both concise and informative. | D75: As a news reader, I want the machine learning system to use various summarization techniques, such as TextRank and LSA-based summarization, to generate concise yet informative summaries of the clustered news articles, enabling me to quickly and efficiently digest news content. | E75: News | F75: News | G75: =IF(F75=Requirements!E75,"true","") -> true | H75: data summarization | K75: data summarization
A76: Participant O | B76: Il sistema deve essere in grado di identificare le caratteristiche genomiche più informative con elevata precisione e recall. | C76: The system should be able to identify the most informative genomic features with high precision and recall. | D76: As a plant scientist, I want the system to identify the most informative genomic features with high precision and recall, so that I can trust the results of the analysis and make informed decisions. | E76: Plant Science | F76: Plant Science | G76: =IF(F76=Requirements!E76,"true","") -> true | H76: subset selection | K76: anomaly detection | L76: classification | M76: entity resolution | N76: regression | O76: representation learning | P76: sentiment analysis
A77: Participant O | B77: Il sistema deve essere in grado di abbinare le caratteristiche genomiche ai corrispondenti dati fenotipici, come l'altezza della pianta, la biomassa o la suscettibilità alle malattie. | C77: The system should be able to match the genomic features with the corresponding phenotypic data, such as plant height, biomass, or disease susceptibility. | D77: As a plant scientist, I want the system to match the genomic features with the corresponding phenotypic data, such as plant height, biomass, or disease susceptibility, so that I can understand the genetic basis of different plant traits. | E77: Plant Science | F77: Plant Science | G77: =IF(F77=Requirements!E77,"true","") -> true | H77: matching | K77: classification
A78: Participant O | B78: Il sistema deve essere in grado di abbinare le caratteristiche genomiche ai dati fenotipici in un tempo non superiore ad un'ora, consentendo ai ricercatori di analizzare e interpretare rapidamente i risultati. | C78: The system should be able to match the genomic features with the phenotypic data in no more than an hour, allowing researchers to quickly analyze and interpret the results. | D78: As a plant scientist, I want the system to match the genomic features with the phenotypic data in no more than an hour, so that I can quickly analyze and interpret the results and plan my next experiment accordingly. | E78: Plant Science | F78: Plant Science | G78: =IF(F78=Requirements!E78,"true","") -> true | H78: matching | K78: classification | L78: clustering | M78: regression | N78: representation learning | O78: sentiment analysis
A79: Participant O | B79: Il sistema deve utilizzare tecniche di selezione delle caratteristiche come "Recursive Feature Elimination" o "Random Forest Importance" per identificare le caratteristiche genomiche più informative. | C79: The system should use feature selection techniques such as "Recursive Feature Elimination" or "Random Forest Importance" to identify the most informative genomic features. | D79: As a plant scientist, I want the system to use feature selection techniques such as "Recursive Feature Elimination" or "Random Forest Importance" to identify the most informative genomic features so that I can focus on the most relevant genetic markers for my research. | E79: Plant Science | F79: Plant Science | G79: =IF(F79=Requirements!E79,"true","") -> true | H79: subset selection | K79: advertising | L79: anomaly detection | M79: bias detection in language models | N79: bias detection in word embeddings | O79: classification | P79: clustering | Q79: data summarization | R79: districting | S79: entity resolution | T79: graph augmentation | U79: graph diffusion | V79: graph mining | W79: machine translation | X79: matching | Y79: pricing | Z79: ranking | AA79: regression | AB79: resource allocation | AC79: sentiment analysis | AD79: spatio-temporal process learning | AE79: speech recognition | AF79: task assignment
A80: Participant O | B80: Il sistema deve utilizzare tecniche di matching come Support Vector Regression o K-Nearest Neighbors. | C80: The system should use matching techniques such as Support Vector Regression or K-Nearest Neighbors. | D80: As a plant scientist, I want the system to use matching techniques such as Support Vector Regression or K-Nearest Neighbors to predict the phenotype of a plant based on its genomic features, so that I can use this information for breeding or crop improvement. | E80: Plant Science | F80: Plant Science | G80: =IF(F80=Requirements!E80,"true","") -> true | H80: matching | K80: ranking
A81: Participant P | B81: The system shall show to the user the district boundaries obtained as final results on the given data in order to provide support for the electoral districting process, using the model as a tool to reduce inequities such as gerrymandering and electoral manipulations and to improve representativeness | C81: The system shall show to the user the district boundaries obtained as final results on the given data in order to provide support for the electoral districting process, using the model as a tool to reduce inequities such as gerrymandering and electoral manipulations and to improve representativeness | D81: As a Political Science official, I want the system to display the final district boundaries obtained from the data, so that I can use the model as a tool to reduce inequities such as gerrymandering and electoral manipulations and improve representativeness. | E81: Political Science | F81: Political Science | G81: =IF(F81=Requirements!E81,"true","") -> true | H81: districting | K81: anomaly detection | L81: clustering | M81: districting | N81: resource allocation | O81: subset selection | P81: task assignment
A82: Participant P | B82: The system shall perform spatio-temporal process learning, using techniques such as recurrent neural network, to analyze historical voting patterns, population growth and other relevant data to create district boundaries, also taking into consideration the prediction of future election behavior, in order to reduce inequity and gerrymandering and to improve accuracy and representativeness | C82: The system shall perform spatio-temporal process learning, using techniques such as recurrent neural network, to analyze historical voting patterns, population growth and other relevant data to create district boundaries, also taking into consideration the prediction of future election behavior, in order to reduce inequity and gerrymandering and to improve accuracy and representativeness | D82: As a Political Science official, I want the system to perform spatio-temporal process learning, using techniques such as recurrent neural networks, to analyze historical voting patterns, population growth, and other relevant data to create district boundaries that take into consideration the prediction of future election behavior. This will help to reduce inequity and gerrymandering and improve accuracy and representativeness. | E82: Political Science | F82: Political Science | G82: =IF(F82=Requirements!E82,"true","") -> true | H82: spatio-temporal process learning | K82: other
A83: Participant P | B83: The system shall validate the trained model and obtain metrics related to the quality of the electoral districting process, like political representation and the fairness and equity of decisions made | C83: The system shall validate the trained model and obtain metrics related to the quality of the electoral districting process, like political representation and the fairness and equity of decisions made | D83: As a Political Science official, I want the system to validate the trained model and obtain metrics related to the quality of the electoral districting process, such as political representation and the fairness and equity of decisions made. | E83: Political Science | F83: Political Science | G83: =IF(F83=Requirements!E83,"true","") -> true | H83: representation learning | I83: districting | K83: ranking
A84: Participant M | B84: Il sistema deve essere in grado di accedere a grandi set di dati di attori e attrici per identificare le caratteristiche fisiche degli attori e delle attrici e assegnare i ruoli in modo scalabile ed efficiente. | C84: The system must be able to access large sets of actor and actress data to identify their physical characteristics and assign roles in a scalable and efficient manner. | D84: As a producer, I want the system to be able to access large sets of actor and actress data to identify their physical characteristics and assign roles in a scalable and efficient manner, so that I can reduce the time and effort required to find suitable candidates. | E84: Movies | F84: Movies | G84: =IF(F84=Requirements!E84,"true","") -> true | H84: task assignment | K84: other
A85: Participant M | B85: Il sistema deve essere in grado di accedere a grandi set di dati di produzione cinematografica per identificare i film di maggior successo, i generi più popolari e le tendenze di produzione in modo da identificare i direttori di casting più adeguati. | C85: The system must be able to access large sets of cinematic production data to identify the most successful films, the most popular genres, and production trends in order to identify the most suitable casting directors. | D85: As a producer, I want the system to be able to access large sets of cinematic production data to identify the most successful films, the most popular genres, and production trends in order to identify the most suitable casting directors, so that I can make more informed decisions when selecting casting directors. | E85: Movies | F85: Movies | G85: =IF(F85=Requirements!E85,"true","") -> true | H85: task assignment | K85: other
A86: Participant M | B86: Il sistema deve utilizzare un algoritmo di filtraggio collaborativo per selezionare gli attori per specifici ruoli in base alle capacità, all’esperienza e all’idoneità. | C86: The system must use a collaborative filtering algorithm to select actors for specific roles based on their abilities, experience, and suitability. | D86: As a producer, I want the system to use a collaborative filtering algorithm to suggest suitable actors for specific roles based on their abilities, experience, and suitability, so that I can make more informed casting decisions and increase the chances of producing successful films. | E86: Movies | F86: Movies | G86: =IF(F86=Requirements!E86,"true","") -> true | H86: task assignment | K86: other
A87: Participant M | B87: Il sistema deve utilizzare una tecnica di filtraggio basato sui contenuti per analizzare le caratteristiche dei direttori del casting e assegnargli specifiche attività di selezione del casting. | C87: The system must use a content-based filtering technique to analyze the characteristics of casting directors and assign them specific casting selection activities. | D87: As a producer, I want the system to use a content-based filtering technique to analyze the characteristics of casting directors and assign them specific casting selection activities, so that I can ensure that the right casting director is assigned to the right project. | E87: Movies | F87: Movies | G87: =IF(F87=Requirements!E87,"true","") -> true | H87: subset selection | K87: other
A88: Participant M | B88: Il sistema deve utilizzare degli algoritmi per la classificazione delle competenze di un direttore di casting, al fine di comprendere similarità tra i candidati e affinità di copertura richieste. | C88: The system must use algorithms for the classification of a casting director's skills to understand similarities between candidates and required coverage affinity. | D88: As a producer, I want the system to use algorithms for the classification of a casting director's skills to understand similarities between candidates and required coverage affinity, so that I can ensure that the right casting director is selected for the right project. | E88: Movies | F88: Movies | G88: =IF(F88=Requirements!E88,"true","") -> true | H88: classification | K88: other
A89: Participant M | B89: Il sistema deve utilizzare la tecnica di analisi semantica (Latent Semantic Analysis) sui curriculum di tutti i direttori di casting per estrarre e analizzare dati significativi, confrontarli con le caratteristiche richieste e utilizzarli per assegnare un direttore di casting ad una specifica attività. | C89: The system must use the technique of semantic analysis (Latent Semantic Analysis) on the resumes of all casting directors to extract and analyze significant data, compare them with the required characteristics and use them to assign a casting director to a specific activity. | D89: As a producer, I want the system to use the technique of semantic analysis (Latent Semantic Analysis) on the resumes of all casting directors to extract and analyze significant data, compare them with the required characteristics, and assign a casting director to a specific activity, so that I can ensure that the right casting director is assigned to the right project. | E89: Movies | F89: Movies | G89: =IF(F89=Requirements!E89,"true","") -> true | H89: subset selection | K89: other
A90: Participant I | B90: Il sistema deve essere in grado di adattarsi ai cambiamenti nella rete sociale per garantire l'efficacia continua delle strategie di pubblicità. | C90: The system must be capable of adapting to changes in the social network to ensure the continuous effectiveness of advertising strategies. | D90: As a product manager, I want the system to adapt to changes in the social network to ensure the continuous effectiveness of advertising strategies and user engagement. | E90: Information Systems | F90: Literature | G90: =IF(F90=Requirements!E90,"true","") | H90: advertising | K90: anomaly detection | L90: graph diffusion | M90: regression | N90: resource allocation | O90: spatio-temporal process learning | P90: subset selection
A91: Participant H | B91: The system shall provide an interactive dashboard that provides users with the ability to customize the input parameters of the machine learning model, such as the time interval considered for price prediction | C91: The system shall provide an interactive dashboard that provides users with the ability to customize the input parameters of the machine learning model, such as the time interval considered for price prediction | D91: As a quant developer, I want an interactive dashboard that allows users to customize the input parameters of the machine learning model, such as the time interval considered for price prediction, so that users can customize the system to their investment needs. | E91: Finance & Marketing | F91: Biology | G91: =IF(F91=Requirements!E91,"true","") | H91: pricing | K91: anomaly detection
A92: Participant H | B92: The system shall provide the ability to select the specific machine learning algorithm for predicting the price of financial products | C92: The system shall provide the ability to select the specific machine learning algorithm for predicting the price of financial products | D92: As a quant researcher, I want the ability to select the specific machine learning algorithm for predicting the price of financial products, so that I can choose the best algorithm for my investment needs. | E92: Finance & Marketing | F92: Biology | G92: =IF(F92=Requirements!E92,"true","") | H92: pricing | I92: regression | K92: classification
A93: Participant H | B93: The system shall be able to handle large volumes of financial and market data, including historical stock prices, economic indicators, and company financial reports to accurately predict the pricing of financial products | C93: The system shall be able to handle large volumes of financial and market data, including historical stock prices, economic indicators, and company financial reports to accurately predict the pricing of financial products | D93: As a quantitative analyst in the finance industry, I want the system to be able to handle large volumes of financial and market data, including historical stock prices, economic indicators, and company financial reports, to accurately predict the pricing of financial products, so that I can rely on the accuracy of the predictions. | E93: Finance & Marketing | F93: Biology | G93: =IF(F93=Requirements!E93,"true","") | H93: regression | I93: spatio-temporal process learning | K93: anomaly detection | L93: bias detection in language models | M93: bias detection in word embeddings | N93: classification | O93: data summarization | P93: districting | Q93: entity resolution | R93: graph mining | S93: machine translation | T93: matching | U93: ranking | V93: regression | W93: representation learning | X93: resource allocation | Y93: sentiment analysis | Z93: spatio-temporal process learning | AA93: speech recognition | AB93: task assignment
A94: Participant Q | B94: Sentiment Analysis Algorithms: The system must use a Sentiment Analysis Algorithms algorithm using the Lexicon-Method Based to determine the sentiment of a sentence by summing the scores of each words contained | C94: Sentiment Analysis Algorithms: The system must use a Sentiment Analysis Algorithms algorithm using the Lexicon-Method Based to determine the sentiment of a sentence by summing the scores of each words contained | D94: As a sentiment analysis expert in Psychology, I want the system to determine the sentiment of a sentence by using the Lexicon-Method Based Sentiment Analysis Algorithms algorithm so that I can analyze the emotional content of text data for psychological research on emotions and cognition. | E94: Psychology | F94: Biology | G94: =IF(F94=Requirements!E94,"true","") | H94: sentiment analysis | K94: entity resolution | L94: machine translation | M94: sentiment analysis
A95: Participant I | B95: Il sistema deve essere in grado di acquisire, elaborare e analizzare dati relativi ad una rete sociale. | C95: The system must be capable of acquiring, processing, and analyzing data related to a social network. | D95: As a social media analyst, I want the system to acquire, process, and analyze data from a social network so that I can identify trends and patterns in user behavior. | E95: Information Systems | F95: Social Media | G95: =IF(F95=Requirements!E95,"true","") | H95: entity resolution | I95: representation learning | K95: classification | L95: machine translation | M95: ranking | N95: regression | O95: sentiment analysis | P95: speech recognition
A96: Participant I | B96: Il sistema deve essere in grado di monitorare la rete sociale per rilevare eventuali cambiamenti nella diffusione dell'informazione. | C96: The system must be capable of monitoring the social network to detect any changes in the diffusion of information. | D96: As a social media manager, I want the system to monitor the social network and detect changes in information diffusion so that I can adjust my social media strategies as needed. | E96: Information Systems | F96: Social Media | G96: =IF(F96=Requirements!E96,"true","") | H96: risk assessment | K96: other
A97: Participant Q | B97: Collect Social Post/Comment/Reaction/Award: The system must be able to access posts from third-party social media such as Twitter and Reddit | C97: Collect Social Post/Comment/Reaction/Award: The system must be able to access posts from third-party social media such as Twitter and Reddit | D97: As a social media researcher in the Psychology field, I want the system to collect social posts, comments, reactions, and awards from third-party social media such as Twitter and Reddit so that I can study the social and emotional dynamics of online interactions in my research on social media and mental health. | E97: Psychology | F97: Social Media | G97: =IF(F97=Requirements!E97,"true","") | H97: sentiment analysis | K97: anomaly detection | L97: bias detection in language models | M97: bias detection in word embeddings | N97: classification | O97: data summarization | P97: entity resolution | Q97: graph mining | R97: machine translation | S97: regression | T97: sentiment analysis | U97: spatio-temporal process learning | V97: speech recognition | W97: subset selection
A98: Participant Q | B98: Graph Mining: The system must use a Graph Mining algorithm to analyze the connection between users and to track 'famous' users | C98: Graph Mining: The system must use a Graph Mining algorithm to analyze the connection between users and to track 'famous' users | D98: As a social network analyst in the Psychology field, I want the system to analyze the connections between users by using a Graph Mining algorithm so that I can understand the social networks and relationships between individuals in my research on social psychology. | E98: Psychology | F98: Social Networks | G98: =IF(F98=Requirements!E98,"true","") | H98: graph mining | K98: anomaly detection | L98: bias detection in language models | M98: bias detection in word embeddings | N98: classification | O98: clustering | P98: data summarization | Q98: graph mining | R98: machine translation | S98: matching | T98: ranking | U98: sentiment analysis
A99: Participant R | B99: As an ML-intensive application, I want to leverage cloud-based computing platforms and big data analytics to handle the massive amounts of data and achieve scalable and efficient regression and ranking for athlete performance predictions. | C99: As an ML-intensive application, I want to leverage cloud-based computing platforms and big data analytics to handle the massive amounts of data and achieve scalable and efficient regression and ranking for athlete performance predictions. | D99: As a software developer, I want to leverage cloud-based computing platforms and big data analytics to achieve scalable and efficient regression and ranking for athlete performance predictions. | E99: Sport | F99: Literature | G99: =IF(F99=Requirements!E99,"true","") | H99: ranking | I99: regression | K99: advertising | L99: anomaly detection | M99: bias detection in language models | N99: bias detection in word embeddings | O99: classification | P99: clustering | Q99: districting | R99: entity resolution | S99: graph mining | T99: pricing | U99: ranking | V99: regression | W99: representation learning | X99: sentiment analysis
A100: Participant R | B100: As an ML-intensive application, I want to implement sophisticated ranking algorithms, such as Elo rating or Bayesian ranking, to evaluate the performance of teams or players based on their past records and predict future outcomes with greater accuracy. | C100: As an ML-intensive application, I want to implement sophisticated ranking algorithms, such as Elo rating or Bayesian ranking, to evaluate the performance of teams or players based on their past records and predict future outcomes with greater accuracy. | D100: As a sports analyst, I want to implement sophisticated ranking algorithms to evaluate the performance of teams or players based on their past records and predict future outcomes with greater accuracy. | E100: Sport | F100: Sport | G100: =IF(F100=Requirements!E100,"true","") -> true | H100: ranking | K100: advertising | L100: ranking
...

Sheet Foglio1
A2: As a biologist, I want the application to provide accurate classification results with a minimum accuracy of 90% for binary classification problems, as evaluated by metrics such as F1-score, Recall, Precision, Accuracy or Mean squared error, so that I can trust the models results and make informed decisions based on the predictions.
A3: As a biologist, I want the application to provide continuous monitoring and evaluation of the machine learning models performance and accuracy, with feedback loops to improve the model over time, so that I can adapt the model to changing biological conditions and improve its performance over time.
A4: As a biologist, I want the application to use interpretability techniques such as feature importance scores, decision trees, or saliency maps to understand the underlying biological mechanisms and validate the models predictions, so that I can gain insights into the biological mechanisms underlying cancer subtypes and identify the genes and pathways driving the classification results.
A5: As a biologist, I want to access large-scale genomic datasets such as The Cancer Genome Atlas (TCGA) or International Cancer Genome Consortium (ICGC) to get the data necessary to perform this task, so that I can analyze a diverse range of cancer types and gain a comprehensive understanding of cancer biology.
A6: As a biologist, I want to leverage cloud-based computing platforms and big data analytics to handle the high dimensionality of omics data and achieve scalable and efficient classification and clustering, so that I can analyze large-scale genomic datasets and gain insights into the mechanisms underlying cancer subtypes.
A7: As a biologist, I want to use data preparation techniques such as sampling, feature selection, data cleaning, parallel processing, and dimensionality reduction to be able to process large-scale omics data, so that I can optimize the performance of the machine learning models and reduce the impact of noise and spurious correlations.
A8: As a biologist, I want to use supervised classification algorithms such as random forest, logistic regression, or deep learning neural networks to classify cancer subtypes based on gene expression profiles, so that I can accurately identify different cancer subtypes and potentially develop targeted therapies.
A9: As a biologist, I want to use unsupervised clustering algorithms such as K-means, hierarchical clustering, or principal component analysis to identify molecular subtypes of cancer based on genomic data, so that I can gain insights into the underlying biological mechanisms driving cancer subtypes.
A10: As a cardiologist, I want it to use ML algorithms for learning spatio-temporal processes so that it can continuously improve its accuracy in detecting and diagnosing cardiac diseases.
A11: As a cardiologist, I want the system to identify patterns in Echo signals that may indicate the presence of cardiac disease so that I can diagnose and treat patients accurately.
A12: As a cardiologist, I want the system to process ECG signals so that I can analyze the electrical activity of a patients heart and detect any abnormalities.
A13: As a cardiologist, I want the system to process Echo signals so that I can analyze the structure and function of a patients heart and detect any abnormalities.
... A120: As an economic analyst, I want the system to extract and collect data from large-scale advertising sources (e.g. online ads, billboards, TV commercials), so that I can analyze and understand the trends and patterns in the advertising industry.
