Workbook

Sheet Sample
B1: User Story | C1: Domain | D1: Machine Learning Keyword
A2: Survey 1 | B2: As an educator, I want to use abstractive summarization to analyze and summarize research on effective teaching methods, so that I can apply the latest research to my own teaching practice. | C2: Education | D2: Abstractive summarization
A3: Survey 1 | B3: As a literary critic or scholar, I want to use extreme learning machine to analyze literary works and predict literary trends and patterns, so that I can provide better analysis and criticism of literary works. | C3: Literature | D3: extreme learning machine
A4: Survey 1 | B4: As an urban planner, I want to use preference learning to identify which urban design elements (e.g., green space, public art) are most preferred by residents in a specific neighborhood. | C4: Urban Studies | D4: preference learning
A5: Survey 1 | B5: As a movie studio, I want to use similarity learning algorithms to analyze audience data and identify similarities between different audience segments, to better understand audience needs and inform casting and marketing decisions. | C5: Movies | D5: similarity learning
A6: Survey 1 | B6: As a demographer, I want to use keyword spotting to identify specific demographic data in large datasets, so that I can better understand population trends and make predictions. | C6: Demography | D6: keyword spotting
A7: Survey 2 | B7: As a sports analyst, I want to use AdaBoost to predict game outcomes and identify key factors that influence team performance to improve sports strategies. | C7: Sport | D7: adaboost
A8: Survey 2 | B8: As a healthcare provider, I want to use learning from demonstration to analyze patient data and identify patterns that may indicate potential health issues, allowing for earlier detection and improved patient outcomes. | C8: Health | D8: learning from demonstration
A9: Survey 2 | B9: As a plant scientist, I want to use a recommendation system to suggest the best crop varieties and cultivation practices for specific environmental conditions and market demand. | C9: Plant Science | D9: recommendation system
A10: Survey 2 | B10: As a sociologist, I want to use multinomial logistic regression to predict social trends and patterns based on social phenomena and behaviors to improve social analysis and understanding. | C10: Sociology | D10: multinomial logistic regression
A11: Survey 2 | B11: As an economist, I want to use BLSTM networks to forecast economic trends and predict market behavior, so that I can help businesses and organizations make informed decisions. | C11: Economics | D11: Bidirectional Long Short-Term Memory
A12: Survey 3 | B12: As a botanist, I want to use sentence generation to automatically generate descriptions of plant species based on their characteristics, to improve our understanding of plant taxonomy and inform botanical research. | C12: Plant Science | D12: sentence generation
A13: Survey 3 | B13: As a nephrologist, I want to use multiple instance learning to identify groups of patients with similar kidney disease characteristics and risk factors based on various patient data sources to improve disease prevention and treatment. | C13: Nephrology | D13: multiple instance learning
... A107: Survey 22 | B107: As a transportation company, I want to use convolutional neural networks to develop image recognition models that can identify and track vehicles, pedestrians, and road signs in real-time video footage. | C107: Transportation | D107: convolutional neural network
A108: =A107 -> Survey 22 | B108: As a demographer, I want to use extreme learning machine to analyze census data and predict population trends and patterns, so that I can make informed policy recommendations. | C108: Demography | D108: extreme learning machine
A109: =A108 -> Survey 22 | B109: As a linguist, I want to summarize linguistic research and reports to quickly identify relevant information for linguistic research and analysis. | C109: Linguistics | D109: text summarization
A110: =A109 -> Survey 22 | B110: As a medical researcher, I want to use n-grams to analyze patterns in medical research publications and clinical trial data, so that I can better understand the state of medical research in specific areas and identify gaps in knowledge. | C110: Medicine | D110: n-grams
A111: =A110 -> Survey 22 | B111: As a movie producer, I want to use action model learning to predict box office success and audience reception, so that I can create more successful movies and maximize profits. | C111: Movies | D111: action model learning
A112: Survey 23 | B112: As a literature scholar, I want to use perceptron to classify literary works based on their genre and style to analyze literary movements and trends. | C112: Literature | D112: perceptron
A113: =A112 -> Survey 23 | B113: As a social network researcher, I want to use voice recognition to analyze audio recordings from social media platforms and identify patterns in language use and communication behaviors, so that I can better understand how people interact with each other online and develop more accurate models of online communication. | C113: Social Networks | D113: voice recognition
A114: =A113 -> Survey 23 | B114: As a nephrologist , I want to use a voice command device to access patient records and control medical equipment so that I can more efficiently and accurately diagnose and treat kidney diseases. | C114: Nephrology | D114: voice command device
A115: =A114 -> Survey 23 | B115: As an educator, I want to use multinomial classification to classify student data based on their performance and characteristics to provide effective personalized learning opportunities. | C115: Education | D115: multinomial classification
A116: =A115 -> Survey 23 | B116: As a transportation analyst, I want to utilize Bayesian learning to analyze traffic patterns and identify the most likely causes of congestion, so that I can recommend the most effective solutions for improving traffic flow. | C116: Transportation | D116: Bayesian Learning
A117: Survey 24 | B117: As a literary scholar, I want to use conditional random fields to predict literary trends and reception based on literary and environmental variables, such as identifying clusters of literary works with high levels of intertextual references or predicting literary movements, so that we can better understand patterns of literary production and reception. | C117: Literature | D117: conditional random field
A118: =A117 -> Survey 24 | B118: As a lawyer, I want to use robot learning to analyze large amounts of legal data, so that I can identify trends and patterns in court decisions and better advise my clients. | C118: Law | D118: robot learning
A119: =A118 -> Survey 24 | B119: As a political scientist, I want to use unsupervised learning to identify patterns in voting data and study the relationship between demographic characteristics and election outcomes. | C119: Political Science | D119: unsupervised learning
A120: =A119 -> Survey 24 | B120: As a social network researcher, I want to use maximum entropy modeling to identify the most influential nodes in a given social network. | C120: Social Networks | D120: maximum entropy modeling
A121: =A120 -> Survey 24 | B121: As a sports organization, I want to use a recommender engine to suggest personalized sports news and content to each fan, based on their interests, team preferences, and social network, using machine learning algorithms. | C121: Sport | D121: recommender engine
A122: Survey 25 | B122: As a dermatologist, I want to use hidden Markov models to analyze the skin lesion patterns and evolution based on the time-series data of dermatological images and patient records to improve the accuracy and efficiency of skin disease diagnosis and treatment. | C122: Dermatology | D122: hidden markov model
A123: =A122 -> Survey 25 | B123: As a dermatologist, I want to use mention detection to identify the most frequently mentioned skin conditions or symptoms in a given medical literature or social media dataset. | C123: Dermatology | D123: mention detection
A124: =A123 -> Survey 25 | B124: As a psychologist, I want to use reinforcement learning to develop better models of mental health treatment and improve patient outcomes. | C124: Psychology | D124: reinforcement learning
A125: =A124 -> Survey 25 | B125: As a dermatologist, I want to utilize document embedding to represent medical images as vectors of skin condition-specific features, so that I can more easily diagnose skin diseases and develop targeted treatment plans. | C125: Dermatology | D125: document embedding
A126: =A125 -> Survey 25 | B126: As a computational biologist, I want to use word embedding techniques to analyze large sets of genomic data and identify common patterns of gene expression, so that I can better understand the underlying regulatory mechanisms that control cell function. | C126: Biology | D126: Word Embedding
A127: Survey 26 | B127: As an information systems analyst, I want to identify multiword expressions in user search queries to improve search engine functionality. | C127: Information Systems | D127: multiword expressions
A128: =A127 -> Survey 26 | B128: As a neuroscientist, I want to use deep networks to analyze large sets of brain imaging data and identify patterns of neural activity associated with different mental states, so that I can better understand the neural basis of human consciousness. | C128: Biology | D128: deep network
A129: =A128 -> Survey 26 | B129: As an urban planner, I want to use multifactor dimensionality reduction to identify the combination of demographic, socio-economic, and land use factors that contribute to urban growth and development, so that I can make more informed decisions about land use and urban planning. | C129: Urban Studies | D129: multifactor dimensionality reduction
A130: =A129 -> Survey 26 | B130: As a sports analyst, I want to use fuzzy neural networks to predict athletic performance and outcomes based on large datasets of athlete data, so that I can better analyze and understand sports performance. | C130: Sport | D130: fuzzy neural network
A131: =A130 -> Survey 26 | B131: As a transportation engineer, I want to use Echo State Networks to predict traffic flow and congestion patterns based on historical sensor data from highways and urban roads, as well as real-time data from connected vehicles and smart infrastructure. | C131: Transportation | D131: echo state network
A132: Survey 27 | B132: As a bioinformatics researcher, I want to use random forest algorithms to analyze large sets of genomic data and identify patterns of gene expression, so that I can better understand the underlying biological mechanisms that control cell function. | C132: Biology | D132: random forest
A133: =A132 -> Survey 27 | B133: As a network administrator, I want to use inductive logic learning to identify patterns in network traffic data, in order to improve network security and performance. | C133: Computer Networks | D133: inductive logic learning
A134: =A133 -> Survey 27 | B134: As a lawyer, I want to use voice activity detection to analyze audio recordings from legal proceedings and identify patterns in speech and language use so that I can better understand how language is used in legal contexts and build stronger arguments for my clients. | C134: Law | D134: voice activity detection
A135: =A134 -> Survey 27 | B135: As a literary analyst, I want to use developmental robotics to analyze literary works and gain insights into the nature of human creativity and expression. | C135: Literature | D135: developmental robotics
A136: =A135 -> Survey 27 | B136: As an educator, I want to use FSS-SVM to select the most informative student features from academic and demographic data, so that I can better predict student performance and improve teaching strategies. | C136: Education | D136: fss-svm
A137: Survey 28 | B137: As an IT professional, I want to use adversarial networks to develop more secure and robust systems that can better defend against cyber attacks, so that we can protect sensitive data and prevent breaches. | C137: Information Systems | D137: adversarial network
A138: =A137 -> Survey 28 | B138: As a public health researcher, I want to use stochastic game theory to model the behavior of different pathogens and their interaction with the immune system to better understand the spread of infectious diseases and design more effective vaccination strategies. | C138: Health | D138: stochastic game
A139: =A138 -> Survey 28 | B139: As a songwriter, I want to use a machine learning system for lexical choice to find the best words and lyrics for my songs, so that I can create more meaningful and powerful music. | C139: Music | D139: lexical choice
A140: =A139 -> Survey 28 | B140: As an educator, I want to use novelty detection to identify unusual patterns of student behavior and engagement, so that we can better understand how to improve education outcomes. | C140: Education | D140: novelty detection
A141: =A140 -> Survey 28 | B141: As an education researcher, I want to use computational linguistics to analyze student essays and identify patterns in language use that may indicate areas where students need additional support. | C141: Education | D141: computational linguistics
A142: Survey 29 | B142: As a demographer, I want to use conceptual clustering to group populations based on demographic characteristics, such as age, gender, and income, to better understand the social and economic dynamics of different regions. | C142: Demography | D142: conceptual clustering
A143: =A142 -> Survey 29 | B143: As a computational biologist, I want to use conditional GANs to generate realistic images of different organisms based on their genetic profiles, so that I can create accurate and comprehensive visual representations of different species and their characteristics. | C143: Biology | D143: Conditional GANs
A144: =A143 -> Survey 29 | B144: As a social network researcher, I want to use sequence labeling to identify and classify different types of user behavior on social networks, such as trolling or hate speech, to better understand the dynamics of online communities and inform social network design decisions. | C144: Social Networks | D144: sequence labeling
A145: =A144 -> Survey 29 | B145: As a network engineer, I want to use multitask learning to simultaneously predict multiple network outcomes, such as network performance and security threats, using different data sources, such as log and network data, to improve network design and security. | C145: Computer Networks | D145: multitask learning
A146: =A145 -> Survey 29 | B146: As a linguist, I want to use classification methods to classify different types of languages, so that I can better understand linguistic patterns. | C146: Linguistics | D146: classification method
A147: Survey 30 | B147: As an information systems analyst, I want to use sigmoid functions to model system behavior based on real-time system data, to better understand and predict system performance and inform system management strategies. | C147: Information Systems | D147: sigmoid function
A148: =A147 -> Survey 30 | B148: As a movie producer, I want to use the k-nearest neighbor algorithm to identify patterns in audience preferences based on demographic and socioeconomic factors, so that I can improve movie production and marketing strategies. | C148: Movies | D148: k-nearest neighbor
A149: =A148 -> Survey 30 | B149: As a plant scientist, I want to use hidden Markov models to analyze the growth patterns and developmental stages of plants based on the time-series data of plant morphology and physiology to improve the understanding of plant growth and development. | C149: Plant Science | D149: hidden markov model
A150: =A149 -> Survey 30 | B150: As a musician, I want to use feature hashing to analyze music data and identify patterns in melody and rhythm, so that I can better understand musical trends and inform my own compositions. | C150: Music | D150: feature hashing
A151: =A150 -> Survey 30 | B151: As an educator, I want to use expectation propagation to personalize learning and predict student performance, so that I can design effective educational programs and support systems. | C151: Education | D151: expectation propagation
A152: Survey 31 | B152: As a literary scholar, I want to use the random subspace method to identify the most important features that affect reader response to novels. | C152: Literature | D152: random subspace method
A153: =A152 -> Survey 31 | B153: As a sports organization, I want to use neural network hardware to analyze sports data and predict athlete performance and game outcomes, so that I can improve player development and game strategy. | C153: Sport | D153: neural network hardware
A154: =A153 -> Survey 31 | B154: As a radiologist, I want to use fake news detection to identify and correct false information and misinformation about medical imaging and diagnosis, so that patients can be better informed and receive appropriate care. | C154: Radiology | D154: fake news detection
A155: =A154 -> Survey 31 | B155: A nephrologist needs to review multiple patient cases to identify potential patterns in kidney disease. They use an automatic summarization tool to generate summaries of each case, allowing them to quickly identify common symptoms and risk factors without having to read each case in full. | C155: Nephrology | D155: Automatic Summarization
A156: =A155 -> Survey 31 | B156: As a nephrologist, I want to use semantic role labeling to identify the roles of different factors in chronic kidney disease progression and develop targeted interventions. | C156: Nephrology | D156: semantic role labeling
A157: Survey 32 | B157: As a nephrologist, I want to use machine learning models to measure the word similarity between patient data related to kidney disease, such as serum creatinine levels and urine protein measurements, so that I can identify common patterns indicative of renal conditions and provide more effective treatment. | C157: Nephrology | D157: word similarity
A158: =A157 -> Survey 32 | B158: As a legal researcher, I want to use RNN architecture to analyze legal data over time, so that we can identify trends and patterns in legal outcomes and design better legal policies and practices. | C158: Law | D158: rnn architecture
A159: =A158 -> Survey 32 | B159: As an urban planner, I want to use fully connected layers to predict urban growth and development based on large datasets of demographic and economic data, so that I can better plan for urban infrastructure and services. | C159: Urban Studies | D159: fully connected layer
A160: =A159 -> Survey 32 | B160: As a transportation planner, I want to use entity extraction to automatically identify and extract key transportation-related entities such as street names, addresses, and geographic coordinates from unstructured transportation data such as traffic reports and accident logs, in order to improve traffic management and accident response times. | C160: Transportation | D160: entity extraction
A161: =A160 -> Survey 32 | B161: As a social worker, I want to clean and preprocess the survey data to remove personally identifiable information and ensure data privacy. | C161: Social Work | D161: data pre-processing
A162: Survey 33 | B162: As a sociologist, I want to use regularization techniques to improve the accuracy of my models of social behavior and better understand how individuals and groups interact. | C162: Sociology | D162: regularization
A163: =A162 -> Survey 33 | B163: As a social media analyst, I want to use attention mechanisms to analyze user behavior and identify patterns of engagement and disengagement, so that we can develop more effective social media strategies. | C163: Social Media | D163: attention mechanism
A164: =A163 -> Survey 33 | B164: As a literary critic, I want to use consensus clustering in machine learning models to identify groups of literary works with similar themes and stylistic features, so that I can better understand literary movements and influences. | C164: Literature | D164: consensus clustering
A165: =A164 -> Survey 33 | B165: As a nephrologist, I want to use dependency parsing to analyze patient data and identify correlations between symptoms and kidney disease diagnoses. | C165: Nephrology | D165: dependency parsing
A166: =A165 -> Survey 33 | B166: As a computer vision researcher, I want to use semantic role labeling to identify the roles of different objects and features in image analysis and classification. | C166: Computer Vision | D166: semantic role labeling
A167: Survey 34 | B167: As an IT professional, I want to use evolutionary robotics to optimize network architecture and improve system performance. | C167: Information Systems | D167: evolutionary robotics
A168: =A167 -> Survey 34 | B168: As a news analyst, I want to use evolutionary learning to forecast news trends and patterns, in order to inform news production and dissemination strategies. | C168: News | D168: evolutionary learning
A169: =A168 -> Survey 34 | B169: As a movie producer, I want to use learning from demonstration to analyze movie performance data and identify which types of movies are likely to be successful, allowing for more informed decisions about which movies to produce and how to market them. | C169: Movies | D169: learning from demonstration
A170: =A169 -> Survey 34 | B170: As a news organization, I want to use natural language semantics to analyze articles and user comments, so that I can identify the underlying themes and connections between different news stories, and deliver more insightful and engaging content. | C170: News | D170: natural language semantics
A171: =A170 -> Survey 34 | B171: As a librarian, I want to use sequence labeling to identify and classify different types of library resources, such as books or articles, to improve organization and retrieval. | C171: Library | D171: sequence labeling
A172: Survey 35 | B172: As a political scientist, I want to use hidden Markov models to analyze the political regime dynamics and outcomes based on the time-series data of political events and institutions to improve the understanding and prediction of political processes. | C172: Political Science | D172: hidden markov model
A173: =A172 -> Survey 35 | B173: As a psychologist, I want to use a recommender engine to suggest personalized treatment plans and interventions for each patient, based on their mental health history, symptoms, and preferences, using machine learning algorithms. | C173: Psychology | D173: recommender engine
A174: =A173 -> Survey 35 | B174: As a literary scholar, I want to use ontology to develop a comprehensive taxonomy of literary genres and styles, so that we can better understand and analyze the diversity of literature. | C174: Literature | D174: ontology
A175: =A174 -> Survey 35 | B175: As a computer vision researcher, I want to use keyword extraction to automatically identify important terms and phrases in visual data and research articles, so that I can better understand current research trends and develop new research ideas. | C175: Computer Vision | D175: keyword extraction
A176: =A175 -> Survey 35 | B176: As an endocrinologist, I want to use neural machine translation to translate and analyze medical research papers and reports from different languages, so that I can stay up-to-date with the latest research and collaborate with researchers from around the world. | C176: Endocrinology | D176: neural machine translation
A177: Survey 36 | B177: As a cardiologist, I want to use stochastic game theory to model the behavior of different cells and proteins in the heart to better understand the dynamics of cardiac arrhythmias and develop more effective treatment strategies. | C177: Cardiology | D177: stochastic game
A178: =A177 -> Survey 36 | B178: As a news editor, I want to use synaptic weight algorithms to predict which news stories are likely to be most popular with readers and optimize editorial content accordingly. | C178: News | D178: synaptic weight
A179: =A178 -> Survey 36 | B179: As a pediatrician, I want to use fully connected layers to predict pediatric outcomes based on large datasets of patient health data, so that I can better diagnose and treat childhood diseases. | C179: Pediatrics | D179: fully connected layer
A180: =A179 -> Survey 36 | B180: As a musician, I want to use Markov decision process to model music preferences for better understanding of audience behavior and music recommendations. | C180: Music | D180: markov decision process
A181: =A180 -> Survey 36 | B181: As a social network researcher, I want to use hierarchical reinforcement learning to optimize the network structure and dynamics based on the hierarchical structure of social network communities to improve the understanding and prediction of social network processes and outcomes. | C181: Social Networks | D181: hierarchical reinforcement learning
A182: Survey 37 | B182: As an educator, I want to use learning under covariate shift models to predict changes in student performance under changing teaching methods. | C182: Education | D182: learning under covariate shift
A183: =A182 -> Survey 37 | B183: As a social network researcher, I want to use learning automata to identify influential users and predict the spread of information through the network. | C183: Social Networks | D183: learning automata
A184: =A183 -> Survey 37 | B184: As a music industry professional, I want to use a classifier to classify different types of music genres, so that I can better target my marketing efforts. | C184: Music | D184: classifier
A185: =A184 -> Survey 37 | B185: As a demographer, I want to use document embedding to represent demographic data as vectors of age-specific features, so that I can better understand demographic trends and patterns. | C185: Demography | D185: document embedding
A186: =A185 -> Survey 37 | B186: As an educator, I want to use inductive logic learning to identify patterns in student performance data, in order to develop more effective teaching strategies and improve student outcomes. | C186: Education | D186: inductive logic learning
A187: Survey 38 | B187: As an economist, I want to use natural language processing to analyze news articles and financial reports, so that I can identify economic trends and forecast future market conditions. | C187: Economics | D187: natural language processing
A188: =A187 -> Survey 38 | B188: As a legal professional, I want to use speech synthesis to generate audio versions of legal documents and briefs, which can help me to improve accessibility for clients with visual impairments. | C188: Law | D188: speech synthesis
A189: =A188 -> Survey 38 | B189: As a transportation engineer, I want to use evolutionary robotics to design autonomous vehicles that can navigate in any environment. | C189: Transportation | D189: evolutionary robotics
A190: =A189 -> Survey 38 | B190: As a pediatrician, I want to use feature sets to group patient data by child health outcomes and demographic characteristics, so that I can better prevent and treat childhood diseases. | C190: Pediatrics | D190: feature sets
A191: =A190 -> Survey 38 | B191: As a demographer, I want to use lifelong machine learning to continuously improve my demographic forecasting models and adapt them to changing demographic trends and patterns, in order to provide more accurate and reliable demographic projections for use in policy planning and resource allocation. | C191: Demography | D191: lifelong machine learning
A192: Survey 39 | B192: As a network engineer, I want to use conditional random fields to predict network security threats based on network behavior and environmental variables, such as identifying clusters of network users with high levels of risk or predicting network intrusion attempts, so that we can better design and evaluate network security systems. | C192: Computer Networks | D192: conditional random field
A193: =A192 -> Survey 39 | B193: As a dermatologist, I want to use word-sense disambiguation to identify the correct meaning of medical terms related to skin health. | C193: Dermatology | D193: word-sense disambiguation
...

Sheet Results
A1: Survey | B1: Participant | C1: User Story | D1: Domain | E1: Machine Learning Keyword | F1: Comprehensibility | G1: Actionability | H1: Realism | I1: Different format [Yes/No] | J1: Alternative
A2: Survey 17 | B2: Participant 11 | C2: As a filmmaker, I want to use music information retrieval to analyze how music is used in movies, so that I can better understand how music contributes to the emotional impact of films and make more effective use of music in my own films. | D2: Movies | E2: music information retrieval | F2: 5 | G2: 5 | H2: 5 | I2: Yes | J2: " As a filmmaker, I want to use music information retrieval to analyze how music is used in movies, so that I can better understand how music is used in the films industry and make more effective use of music in my own films. "
A3: Survey 12 | B3: Participant 11 | C3: As a medical researcher, I want to use explicit semantic analysis to analyze medical literature and identify relevant research on diseases and treatments, so that I can develop better therapies and treatments. | D3: Medicine | E3: explicit semantic analysis | F3: 5 | G3: 4 | H3: 3 | I3: Yes | J3: " As a medical researcher, I want to use explicit semantic analysis to analyze recent medical literature and identify relevant research on diseases and treatments, so that I can develop better therapies and treatments. "
A4: =A3 -> Survey 12 | B4: Participant 11 | C4: As a news editor, I want to use synaptic weight algorithms to predict which news stories are likely to be most popular with readers and optimize editorial content accordingly. | D4: News | E4: synaptic weight | F4: 5 | G4: 5 | H4: 5 | I4: Yes | J4: " As a news editor, I want to use weight algorithms to predict which news stories are likely to be most popular with readers and optimize editorial content accordingly."
A5: =A4 -> Survey 12 | B5: Participant 37 | C5: As a medical researcher, I want to use mixture models to analyze patient data and medical research findings and identify different types of diseases and their potential causes, in order to develop more effective treatment plans and preventive strategies. | D5: Medicine | E5: mixture model | F5: 3 | G5: 4 | H5: 3 | I5: Yes | J5: "As a medical researcher, I want to use mixture models for in-depth analysis of patient data and medical research findings. By identifying distinct disease types and their potential underlying causes, I aim to develop more effective and personalized treatment plans and preventive strategies."
A6: Survey 34 | B6: Participant 13 | C6: As an IT professional, I want to use evolutionary robotics to optimize network architecture and improve system performance. | D6: Information Systems | E6: evolutionary robotics | F6: 5 | G6: 4 | H6: 3 | I6: Yes | J6: "As an IT professional, I want to use x or y technology to optimize network...." should be more specific
A7: =A6 -> Survey 34 | B7: Participant 18 | C7: As a computer vision researcher, I need to use a deep belief network to identify patterns in visual data and predict object recognition and segmentation. | D7: Computer Vision | E7: deep belief network | F7: 4 | G7: 3 | H7: 4 | I7: Yes | J7: As a computer vision researcher, I want to leverage deep belief networks to analyze visual data, identify intricate patterns, and achieve high-performance object recognition and segmentation.
A8: =A7 -> Survey 34 | B8: Participant 38 | C8: As a demographer, I want to use neural machine translation to translate and analyze demographic data from different countries and regions, so that I can better understand population trends and migration patterns. | D8: Demography | E8: neural machine translation | F8: 4 | G8: 3 | H8: 4 | I8: Yes | J8: As a demographer, I aim to develop a neural machine translation model that can accurately translate and analyze demographic data from diverse countries and regions. The objective is to gain deeper insights into population trends, migration patterns, and demographic changes across different geographic areas. By effectively utilizing neural machine translation, I can enhance the comparability of demographic data, leading to more comprehensive and informed demographic analyses.
A9: Survey 45 | B9: Participant 38 | C9: As a dermatologist, I want to use neural cryptography to secure and protect confidential medical data related to skin diseases and conditions, so that I can maintain patient privacy and prevent data breaches. | D9: Dermatology | E9: neural cryptography | F9: 4 | G9: 3 | H9: 4 | I9: Yes | J9: As a dermatologist, I want to implement a neural cryptography-based system that ensures the secure storage and transmission of confidential medical data related to skin diseases and conditions. This will help maintain patient privacy, prevent data breaches, and comply with data protection regulations.
A10: =A9 -> Survey 45 | B10: Participant 18 | C10: As a film critic, I want to use latent Dirichlet allocation to identify latent topics in movie reviews related to cinematography, so that I can better understand the critical landscape and identify potential areas for further analysis. | D10: Movies | E10: latent dirichlet allocation | F10: 4 | G10: 3 | H10: 4 | I10: Yes | J10: As a film critic, I want to employ latent Dirichlet allocation to uncover underlying topics and themes in movie reviews, specifically focusing on aspects related to cinematography. By doing so, I aim to gain deeper insights into the critical reception of films and identify potential avenues for further investigation.
A11: =A10 -> Survey 45 | B11: Participant 38 | C11: As a journalist, I want to use stochastic game theory to model the behavior of different news outlets to better understand the impact of different editorial policies on news coverage. | D11: News | E11: stochastic game | F11: 4 | G11: 3 | H11: 4 | I11: Yes | J11: As a journalist, I want to develop a stochastic game theory-based model that analyzes the behavior of different news outlets. The goal is to gain insights into how their editorial policies influence news coverage and the public's perception. By understanding these dynamics, I can better inform my reporting and contribute to a more informed public discourse.
A12: Survey 1 | B12: Participant 2 | C12: As a literary critic or scholar, I want to use extreme learning machine to analyze literary works and predict literary trends and patterns, so that I can provide better analysis and criticism of literary works. | D12: Literature | E12: extreme learning machine | F12: 2 | G12: 2 | H12: 1 | I12: Yes | J12: As a literary critic or scholar, I want to use machine learning to analyze literary works and predict literary trends and patterns, so that I can provide better analysis and criticism of literary works.
A13: =A12 -> Survey 1 | B13: Participant 18 | C13: As a nephrologist, I want to use lexical entailment to identify and analyze the relationships between different kidney-related concepts. | D13: Nephrology | E13: lexical entailment | F13: 4 | G13: 3 | H13: 4 | I13: Yes | J13: As a nephrologist, I want to leverage lexical entailment techniques to automatically discover and explore the underlying semantic relationships between various medical terms and concepts related to kidney diseases and treatments.
A14: =A13 -> Survey 1 | B14: Participant 38 | C14: As a pediatrician, I want to use keyphrase extraction to automatically extract important terms and phrases from patient medical records and research articles, so that I can better understand pediatric health trends and provide more effective care. | D14: Pediatrics | E14: keyphrase extraction | F14: 5 | G14: 4 | H14: 5 | I14: Yes | J14: As a pediatrician, I aim to implement keyphrase extraction techniques to automatically identify and extract crucial terms and phrases from patient medical records and relevant research articles. By leveraging keyphrase extraction, I intend to gain deeper insights into pediatric health trends and improve the effectiveness of medical care for my young patients.
A15: =A14 -> Survey 1 | B15: Participant 38 | C15: As a radiologist - I want to use relational learning to develop more accurate medical image analysis models and better understand the relationships between different health variables. | D15: Radiology | E15: relational learning | F15: 4 | G15: 4 | H15: 5 | I15: Yes | J15: As a radiologist, I aim to implement relational learning techniques to enhance the accuracy of medical image analysis models and gain deeper insights into the relationships between various health variables. By leveraging relational learning, I intend to improve diagnostic precision and contribute to a more comprehensive understanding of medical imaging data for better patient care and treatment outcomes.
A16: =A15 -> Survey 1 | B16: Participant 22 | C16: As a sports analyst, I want to use computational argumentation to analyze and evaluate the effectiveness of different strategies used in sports. | D16: Sport | E16: computational argumentation | F16: 3 | G16: 2 | H16: 1 | I16: Yes | J16: As a sports analyst, I want to use computation argumentation to analyze and evaluate X value, X value, X value in strategies used in sports, in order to evaluate the effectiveness of each strategy.
A17: Survey 3 | B17: Participant 6 | C17: As an endocrinologist, I want to use part-of-speech tagging to analyze patient records to identify the most commonly used words and phrases related to hormone levels and disorders. | D17: Endocrinology | E17: part-of-speech | F17: 3 | G17: 2 | H17: 2 | I17: Yes | J17: As an endocrinologist, I can to use part-of-speech tagging to analyze patientr ecords to identify the most commonly used words and phrases related to hormone levels and disorders.This will help me to improve the overall treatment approach for my patients.
A18: Survey 16 | B18: Participant 9 | C18: As a linguist, I want to use supervised deep networks to predict and analyze language acquisition and use based on linguistic data. | D18: Linguistics | E18: supervised deep networks | F18: 4 | G18: 3 | H18: 2 | I18: Yes | J18: Be a bit more accurate.
A19: Survey 5 | B19: Participant 9 | C19: As a computer vision researcher, I want to use natural language generation to generate reports on image and video processing algorithms, so that I can more easily communicate my findings to other researchers and the wider computer vision community. | D19: Computer Vision | E19: natural language generation | F19: 4 | G19: 3 | H19: 3 | I19: Yes | J19: Be more realistic regarding what it is that he wants to change
A20: =A19 -> Survey 5 | B20: Participant 14 | C20: As a healthcare provider, I want to use summarization to quickly analyze patient records and medical literature to inform my treatment decisions. | D20: Health | E20: summarization | F20: 4 | G20: 2 | H20: 3 | I20: Yes | J20: Categorizer the treatments for all the type for obtain better results
A21: =A20 -> Survey 5 | B21: Participant 44 | C21: As a librarian, I want to use canonical correlation analysis to identify the relationship between book circulation patterns and patron demographics. | D21: Library | E21: canonical correlation analysis | F21: 3 | G21: 5 | H21: 4 | I21: Yes | J21: Create library cards that patrons would use to borrow books. Link demographics of patrons to the library.
A22: =A21 -> Survey 5 | B22: Participant 14 | C22: As a computer vision researcher, I want to use machine learning models to analyze imbalanced datasets of images and video, in order to develop more accurate and efficient computer vision algorithms for a wide range of applications. | D22: Computer Vision | E22: imbalanced dataset | F22: 5 | G22: 4 | H22: 4 | I22: Yes | J22: Explain and use CNN for the classification
A23: Survey 10 | B23: Participant 14 | C23: As a sports analyst, I want to use neocognitron to recognize and classify visual content in sports events, so that I can analyze and compare different games and players. | D23: Sport | E23: neocognitron | F23: 4 | G23: 2 | H23: 3 | I23: Yes | J23: Explain more exactly the type of label you need to analyzer
A24: Survey 21 | B24: Participant 14 | C24: As a librarian, I want to use structured output to predict the optimal placement of a particular book based on various factors such as genre, author popularity, and borrowing history. | D24: Library | E24: structured output | F24: 1 | G24: 3 | H24: 1 | I24: Yes | J24: Explain more of the problem and general more the problem
A25: Survey 24 | B25: Participant 14 | C25: As a literary scholar, I want to use conditional random fields to predict literary trends and reception based on literary and environmental variables, such as identifying clusters of literary works with high levels of intertextual references or predicting literary movements, so that we can better understand patterns of literary production and reception. | D25: Literature | E25: conditional random field | F25: 1 | G25: 3 | H25: 4 | I25: Yes | J25: Explain the type of values for work used much literary bur not say nothing about the problem
A26: Survey 60 | B26: Participant 14 | C26: As a social worker, I want to use NooJ to analyze social policy data and identify patterns in social issues, so that we can better understand the broader social context in which we work. | D26: Social Work | E26: nooj | F26: 2 | G26: 1 | H26: 1 | I26: Yes | J26: He need reorganizer the problem for identify the data for solved the problem is very general and complicated for obtain results
A27: Survey 3 | B27: Participant 5 | C27: As an endocrinologist, I want to use part-of-speech tagging to analyze patient records to identify the most commonly used words and phrases related to hormone levels and disorders. | D27: Endocrinology | E27: part-of-speech | F27: 2 | G27: 3 | H27: 2 | I27: No | J27: I did not understand the relationship between speech and hormones
A28: Survey 18 | B28: Participant 5 | C28: As an endocrinologist, I want to use speech recognition to transcribe patient histories and medical notes, which can help me to easily reference the content and improve patient care efficiency. | D28: Endocrinology | E28: speech recognition | F28: 4 | G28: 5 | H28: 4 | I28: Yes | J28: I did not understand the relationship between speech recognition and hormones
A29: =A28 -> Survey 18 | B29: Participant 5 | C29: As a dermatologist, I want to use word-sense disambiguation to identify the correct meaning of medical terms related to skin health. | D29: Dermatology | E29: word-sense disambiguation | F29: 2 | G29: 1 | H29: 1 | I29: No | J29: I did not understand the relationship between word-sense and skin health
A30: Survey 6 | B30: Participant 5 | C30: As a network administrator, I want to use voice activity detection to analyze network traffic and identify patterns in speech and language use so that I can detect and prevent security threats that involve voice and audio data. | D30: Computer Networks | E30: voice activity detection | F30: 2 | G30: 3 | H30: 1 | I30: No | J30: I don't understand the relation between network traffic and patterns in speech and language
A31: Survey 16 | B31: Participant 9 | C31: As an IT professional, I want to use convolutional neural networks to develop computer vision models that can detect and analyze anomalies in network traffic, enabling more effective network security. | D31: Information Systems | E31: convolutional neural network | F31: 1 | G31: 2 | H31: 1 | I31: Yes | J31: I personally don't think in the form of health that this would be more beneficial
A32: Survey 10 | B32: Participant 15 | C32: As a linguist, I want to use evolutionary robotics to simulate language evolution and study the origins of language. | D32: Linguistics | E32: evolutionary robotics | F32: 4 | G32: 3 | H32: 4 | I32: Yes | J32: I think the definition of language can be troublesome here, and which language it is talking about.
A33: =A32 -> Survey 10 | B33: Participant 9 | C33: As a political scientist, I want to use stemming algorithms to analyze political speeches and identify related topics and concepts, so that I can better understand and predict political trends and patterns. | D33: Political Science | E33: stemming | F33: 2 | G33: 3 | H33: 2 | I33: Yes | J33: In some way this is unrealistic
A34: =A33 -> Survey 10 | B34: Participant 14 | C34: As a literary scholar, I want to use ontology to develop a comprehensive taxonomy of literary genres and styles, so that we can better understand and analyze the diversity of literature. | D34: Literature | E34: ontology | F34: 5 | G34: 2 | H34: 2 | I34: Yes | J34: Need more explain that the type of data need for obtain results
A35: Survey 57 | B35: Participant 14 | C35: As a social media marketer, I want to use sentence generation to automatically generate social media posts and advertisements, to improve engagement with target audiences and enhance brand awareness. | D35: Social Media | E35: sentence generation | F35: 4 | G35: 2 | H35: 4 | I35: Yes | J35: Need more explanation of the type of info that used for generate the answer
A36: =A35 -> Survey 57 | B36: Participant 14 | C36: As a social network researcher, I want to use maximum entropy modeling to identify the most influential nodes in a given social network. | D36: Social Networks | E36: maximum entropy modeling | F36: 2 | G36: 4 | H36: 3 | I36: Yes | J36: Need to explain more the problem
A37: Survey 68 | B37: Participant 14 | C37: As a network analyst, I want to use Kohonen neural networks to identify patterns in social network data, so that I can better understand network behavior and develop more effective network analysis strategies. | D37: Social Networks | E37: kohonen neural network | F37: 2 | G37: 3 | H37: 2 | I37: Yes | J37: Need to explain more the problem and the data for used
A38: Survey 7 | B38: Participant 9 | C38: As a public health researcher, I want to use binary classification models to predict disease outbreaks and track the spread of infectious diseases, so that I can better understand and respond to public health threats. | D38: Health | E38: binary classification | F38: 3 | G38: 4 | H38: 3 | I38: Yes | J38: Provide more details as to how you are going to by doing this, or will this take place in the form of human test-subjects?
A39: Survey 10 | B39: Participant 14 | C39: As a sociologist, I want to use a learning-based method to analyze social trends and predict changes in societal behavior, so that I can provide insights to policymakers and help shape public policy. | D39: Sociology | E39: learning-based method | F39: 4 | G39: 2 | H39: 1 | I39: Yes | J39: The idea need be more general explain exactly the type of data is very general the info
A40: Survey 5 | B40: Participant 9 | C40: As a network engineer, I want to use sentence generation to automatically generate network documentation and support materials, to improve network efficiency and reduce support requests. | D40: Computer Networks | E40: sentence generation | F40: 4 | G40: 2 | H40: 3 | I40: Yes | J40: there are permissions to adhere to when completing these sentence generation
A41: Survey 71 | B41: Participant 9 | C41: As a journalist, I want to use a probabilistic neural network to predict the likelihood of a news story being popular based on historical data and current events. | D41: News | E41: probabilistic neural network | F41: 2 | G41: 2 | H41: 1 | I41: Yes | J41: This is very unrealistic
A42: Survey 67 | B42: Participant 46 | C42: As a political scientist, I want to use discourse relation analysis to identify the relationships between different political ideologies, movements, and policies, and to understand how these factors influence political discourse and decision-making. | D42: Political Science | E42: discourse relation | F42: 3 | G42: 2 | H42: 2 | I42: Yes | J42: to not put all the example in one sentence so you can explain each so the user can understand each one when explained
A43: Survey 10 | B43: Participant 15 | C43: As a pediatrician, I want to use string kernel methods to analyze patterns in patient data, such as medical records and test results, and identify common trends in pediatric diseases, such as childhood cancers and genetic disorders, in order to develop more effective treatment strategies and improve patient outcomes. | D43: Pediatrics | E43: string kernel | F43: 3 | G43: 2 | H43: 3 | I43: Yes | J43: Too much information and connections with different factors. Should be simplified.
A44: Survey 35 | B44: Participant 14 | C44: As a political scientist, I want to use hidden Markov models to analyze the political regime dynamics and outcomes based on the time-series data of political events and institutions to improve the understanding and prediction of political processes. | D44: Political Science | E44: hidden markov model | F44: 4 | G44: 3 | H44: 1 | I44: Yes | J44: Use a neuronal network with a data provide better result that Markov
A45: =A44 -> Survey 35 | B45: Participant 14 | C45: As a transportation planner, I want to use NLP to analyze transportation data and identify patterns and trends in traffic and transportation behavior, so that we can make informed decisions about transportation policy and infrastructure development. | D45: Transportation | E45: nlp | F45: 4 | G45: 3 | H45: 4 | I45: Yes | J45: Use CNN to identify the people is more common in this case and obtain better results
A46: =A45 -> Survey 35 | B46: Participant 14 | C46: As a news organization, I want to use SVM classifier to classify news articles into different categories such as politics, sports, and entertainment, based on various textual features such as headline and content, so that I can organize news content and improve user engagement. | D46: News | E46: svm classifier | F46: 5 | G46: 4 | H46: 2 | I46: Yes | J46: Use NN is more fast used labels for the classification
A47: =A46 -> Survey 35 | B47: Participant 9 | C47: As a pharmacologist, I want to use explicit semantic analysis to analyze drug literature and identify relevant research on drug efficacy and side effects, so that I can develop better drugs and treatment plans. | D47: Pharmacology | E47: explicit semantic analysis | F47: 4 | G47: 3 | H47: 4 | I47: Yes | J47: Who would be the test patients?
A48: Survey 7 | B48: Participant 9 | C48: As a music analyst, I want to preprocess the music data to remove any errors and inconsistencies before analyzing the musical features. | D48: Music | E48: data pre-processing | F48: 3 | G48: 3 | H48: 1 | I48: Yes | J48: You going to need your music features before you can decide whether or not to add or remove anything.
A49: Survey 1 | B49: Participant 1 | C49: As a demographer, I want to use keyword spotting to identify specific demographic data in large datasets, so that I can better understand population trends and make predictions. | D49: Demography | E49: keyword spotting | F49: 4 | G49: 5 | H49: 4 | I49: No
A50: Survey 1 | B50: Participant 1 | C50: As a literary critic or scholar, I want to use extreme learning machine to analyze literary works and predict literary trends and patterns, so that I can provide better analysis and criticism of literary works. | D50: Literature | E50: extreme learning machine | F50: 5 | G50: 5 | H50: 5 | I50: Yes
A51: Survey 1 | B51: Participant 1 | C51: As a movie studio, I want to use similarity learning algorithms to analyze audience data and identify similarities between different audience segments, to better understand audience needs and inform casting and marketing decisions. | D51: Movies | E51: similarity learning | F51: 5 | G51: 5 | H51: 5 | I51: No
A52: Survey 1 | B52: Participant 1 | C52: As an educator, I want to use abstractive summarization to analyze and summarize research on effective teaching methods, so that I can apply the latest research to my own teaching practice. | D52: Education | E52: Abstractive summarization | F52: 4 | G52: 5 | H52: 3 | I52: No
A53: Survey 1 | B53: Participant 1 | C53: As an urban planner, I want to use preference learning to identify which urban design elements (e.g., green space, public art) are most preferred by residents in a specific neighborhood. | D53: Urban Studies | E53: preference learning | F53: 4 | G53: 5 | H53: 4 | I53: No
A54: Survey 5 | B54: Participant 10 | C54: As a news analyst, I want to use boosting methods to predict and analyze news trends and user engagement, so that I can better understand and target news stories to specific audiences. | D54: News | E54: boosting method | F54: 5 | G54: 5 | H54: 4 | I54: No
A55: Survey 5 | B55: Participant 10 | C55: As a computer vision researcher, I want to use natural language generation to generate reports on image and video processing algorithms, so that I can more easily communicate my findings to other researchers and the wider computer vision community. | D55: Computer Vision | E55: natural language generation | F55: 4 | G55: 4 | H55: 4 | I55: No
A56: Survey 5 | B56: Participant 10 | C56: As a medical researcher, I want to use latent semantic analysis to identify related research articles on clinical trials for various diseases, so that I can better understand the research landscape and identify potential areas for further study. | D56: Medicine | E56: latent semantic analysis | F56: 5 | G56: 4 | H56: 4 | I56: No
A57: Survey 5 | B57: Participant 10 | C57: As a network engineer, I want to use sentence generation to automatically generate network documentation and support materials, to improve network efficiency and reduce support requests. | D57: Computer Networks | E57: sentence generation | F57: 4 | G57: 3 | H57: 4 | I57: No
A58: Survey 5 | B58: Participant 10 | C58: As a dermatologist, I want to use semantic web data to access and analyze medical data across different sources and regions, and identify patterns and relationships in skin diseases and treatments that can inform medical research and practice. | D58: Dermatology | E58: semantic web data | F58: 4 | G58: 3 | H58: 3 | I58: No
A59: Survey 9 | B59: Participant 10 | C59: As a linguist, I want to use statistical relational learning to analyze language data and model language structures and relationships, so that I can better understand and explain language evolution and use across different cultures. | D59: Linguistics | E59: statistical relational learning | F59: 4 | G59: 4 | H59: 5 | I59: No
A60: Survey 9 | B60: Participant 10 | C60: As a network engineer, I want to use feature hashing to analyze network traffic data and identify patterns of usage and potential security threats, so that I can better optimize network performance and prevent attacks. | D60: Computer Networks | E60: feature hashing | F60: 5 | G60: 5 | H60: 5 | I60: No
... A79: Survey 23 | B79: Participant 10 | C79: As a literature scholar, I want to use perceptron to classify literary works based on their genre and style to analyze literary movements and trends. | D79: Literature | E79: perceptron | F79: 4 | G79: 4 | H79: 3 | I79: No
A80: =A79 -> Survey 23 | B80: Participant 10 | C80: As a social network researcher, I want to use voice recognition to analyze audio recordings from social media platforms and identify patterns in language use and communication behaviors, so that I can better understand how people interact with each other online and develop more accurate models of online communication. | D80: Social Networks | E80: voice recognition | F80: 5 | G80: 5 | H80: 5 | I80: No
A81: =A80 -> Survey 23 | B81: Participant 10 | C81: As a nephrologist , I want to use a voice command device to access patient records and control medical equipment so that I can more efficiently and accurately diagnose and treat kidney diseases. | D81: Nephrology | E81: voice command device | F81: 4 | G81: 4 | H81: 3 | I81: No
A82: =A81 -> Survey 23 | B82: Participant 10 | C82: As an educator, I want to use multinomial classification to classify student data based on their performance and characteristics to provide effective personalized learning opportunities. | D82: Education | E82: multinomial classification | F82: 4 | G82: 4 | H82: 3 | I82: No
A83: =A82 -> Survey 23 | B83: Participant 10 | C83: As a transportation analyst, I want to utilize Bayesian learning to analyze traffic patterns and identify the most likely causes of congestion, so that I can recommend the most effective solutions for improving traffic flow. | D83: Transportation | E83: Bayesian Learning | F83: 4 | G83: 3 | H83: 3 | I83: No
A84: Survey 30 | B84: Participant 10 | C84: As an information systems analyst, I want to use sigmoid functions to model system behavior based on real-time system data, to better understand and predict system performance and inform system management strategies. | D84: Information Systems | E84: sigmoid function | F84: 5 | G84: 5 | H84: 4 | I84: No
A85: =A84 -> Survey 30 | B85: Participant 10 | C85: As a movie producer, I want to use the k-nearest neighbor algorithm to identify patterns in audience preferences based on demographic and socioeconomic factors, so that I can improve movie production and marketing strategies. | D85: Movies | E85: k-nearest neighbor | F85: 3 | G85: 4 | H85: 1 | I85: No
A86: =A85 -> Survey 30 | B86: Participant 10 | C86: As a plant scientist, I want to use hidden Markov models to analyze the growth patterns and developmental stages of plants based on the time-series data of plant morphology and physiology to improve the understanding of plant growth and development. | D86: Plant Science | E86: hidden markov model | F86: 5 | G86: 4 | H86: 4 | I86: No
A87: =A86 -> Survey 30 | B87: Participant 10 | C87: As a musician, I want to use feature hashing to analyze music data and identify patterns in melody and rhythm, so that I can better understand musical trends and inform my own compositions. | D87: Music | E87: feature hashing | F87: 4 | G87: 4 | H87: 3 | I87: No
A88: =A87 -> Survey 30 | B88: Participant 10 | C88: As an educator, I want to use expectation propagation to personalize learning and predict student performance, so that I can design effective educational programs and support systems. | D88: Education | E88: expectation propagation | F88: 3 | G88: 3 | H88: 2 | I88: No
A89: Survey 38 | B89: Participant 10 | C89: As an economist, I want to use natural language processing to analyze news articles and financial reports, so that I can identify economic trends and forecast future market conditions. | D89: Economics | E89: natural language processing | F89: 4 | G89: 5 | H89: 4 | I89: No
A90: =A89 -> Survey 38 | B90: Participant 10 | C90: As a legal professional, I want to use speech synthesis to generate audio versions of legal documents and briefs, which can help me to improve accessibility for clients with visual impairments. | D90: Law | E90: speech synthesis | F90: 4 | G90: 4 | H90: 4 | I90: No
A91: =A90 -> Survey 38 | B91: Participant 10 | C91: As a transportation engineer, I want to use evolutionary robotics to design autonomous vehicles that can navigate in any environment. | D91: Transportation | E91: evolutionary robotics | F91: 3 | G91: 3 | H91: 4 | I91: No
A92: =A91 -> Survey 38 | B92: Participant 10 | C92: As a pediatrician, I want to use feature sets to group patient data by child health outcomes and demographic characteristics, so that I can better prevent and treat childhood diseases. | D92: Pediatrics | E92: feature sets | F92: 5 | G92: 5 | H92: 4 | I92: No
A93: =A92 -> Survey 38 | B93: Participant 10 | C93: As a demographer, I want to use lifelong machine learning to continuously improve my demographic forecasting models and adapt them to changing demographic trends and patterns, in order to provide more accurate and reliable demographic projections for use in policy planning and resource allocation. | D93: Demography | E93: lifelong machine learning | F93: 5 | G93: 5 | H93: 5 | I93: No
A94: Survey 45 | B94: Participant 10 | C94: As a dermatologist, I want to use neural cryptography to secure and protect confidential medical data related to skin diseases and conditions, so that I can maintain patient privacy and prevent data breaches. | D94: Dermatology | E94: neural cryptography | F94: 4 | G94: 4 | H94: 2 | I94: No
A95: =A94 -> Survey 45 | B95: Participant 10 | C95: As a journalist, I want to use stochastic game theory to model the behavior of different news outlets to better understand the impact of different editorial policies on news coverage. | D95: News | E95: stochastic game | F95: 4 | G95: 5 | H95: 3 | I95: No
A96: =A95 -> Survey 45 | B96: Participant 10 | C96: As a demographer, I want to use neural machine translation to translate and analyze demographic data from different countries and regions, so that I can better understand population trends and migration patterns. | D96: Demography | E96: neural machine translation | F96: 4 | G96: 3 | H96: 3 | I96: No
A97: =A96 -> Survey 45 | B97: Participant 10 | C97: As a lawyer, I want to use semantic role labeling to identify the roles of different legal concepts and arguments in legal cases and research. | D97: Law | E97: semantic role labeling | F97: 3 | G97: 4 | H97: 4 | I97: No
A98: =A97 -> Survey 45 | B98: Participant 10 | C98: As a sports analyst, I want to use relevance vector machines to analyze sports data and identify key factors that contribute to player performance, so that we can design better training programs and make more informed player draft selections. | D98: Sport | E98: relevance vector machine | F98: 5 | G98: 5 | H98: 5 | I98: No
A99: Survey 68 | B99: Participant 10 | C99: As a network analyst, I want to use Kohonen neural networks to identify patterns in social network data, so that I can better understand network behavior and develop more effective network analysis strategies. | D99: Social Networks | E99: kohonen neural network | F99: 4 | G99: 4 | H99: 4 | I99: No
A100: =A99 -> Survey 68 | B100: Participant 10 | C100: As a marketer, I want to use learning in probabilistic graphical models to better understand consumer behavior and preferences, allowing for more effective targeting and personalized advertising campaigns. | D100: Finance & Marketing | E100: learning in probabilistic graphical model | F100: 5 | G100: 5 | H100: 4 | I100: No
A101: =A100 -> Survey 68 | B101: Participant 10 | C101: As a healthcare provider, I want to use summarization to quickly analyze patient records and medical literature to inform my treatment decisions. | D101: Health | E101: summarization | F101: 4 | G101: 4 | H101: 4 | I101: No
A102: =A101 -> Survey 68 | B102: Participant 10 | C102: As a political scientist, I want to use Rademacher complexity to evaluate the complexity and generalization performance of different machine learning models for political analysis and prediction, in order to better understand political behavior and inform political strategy. | D102: Political Science | E102: rademacher complexity | F102: 4 | G102: 4 | H102: 3 | I102: No
A103: =A102 -> Survey 68 | B103: Participant 10 | C103: As a social media analyst, I want to use learning in probabilistic graphical models to understand how users interact with different types of content and predict which types of posts are most engaging and effective at driving user behavior, allowing for more effective social media marketing and content strategies. | D103: Social Media | E103: learning in probabilistic graphical model | F103: 5 | G103: 5 | H103: 4 | I103: No
A104: Survey 6 | B104: Participant 11 | C104: As a movie critic, I want to use semantic parsing to analyze movie reviews and predict box office success. | D104: Movies | E104: semantic parsing | F104: 5 | G104: 5 | H104: 5 | I104: No
A105: Survey 6 | B105: Participant 11 | C105: As a cardiologist, I want to use domain adaptation techniques to adapt models trained on one patient population to another, so that I can better diagnose and treat different patient populations. | D105: Cardiology | E105: domain adaptation | F105: 4 | G105: 4 | H105: 4 | I105: No
A106: Survey 6 | B106: Participant 11 | C106: As a literary critic, I want to use semantic web data to access and analyze literary data across different sources and regions, and identify patterns and trends in literary genres and styles that can inform literary analysis and theory development. | D106: Literature | E106: semantic web data | F106: 5 | G106: 5 | H106: 4 | I106: No
A107: Survey 6 | B107: Participant 11 | C107: As an economist, I want to use CNNs to classify different types of economic data based on their patterns and trends, so that I can better understand economic dynamics and develop targeted economic policies. | D107: Economics | E107: cnn | F107: 5 | G107: 5 | H107: 3 | I107: No
A108: Survey 6 | B108: Participant 11 | C108: As a network administrator, I want to use voice activity detection to analyze network traffic and identify patterns in speech and language use so that I can detect and prevent security threats that involve voice and audio data. | D108: Computer Networks | E108: voice activity detection | F108: 5 | G108: 5 | H108: 2 | I108: Yes
A109: Survey 12 | B109: Participant 11 | C109: As a sociologist, I want to use dependency parsing to analyze language use and social interaction patterns. | D109: Sociology | E109: dependency parsing | F109: 5 | G109: 5 | H109: 5 | I109: No
A110: Survey 12 | B110: Participant 11 | C110: As a sociologist, I want to use tf-idf analysis to identify the most informative terms in a corpus of survey data, so that I can better understand the relationships between demographic factors and social attitudes. | D110: Sociology | E110: tf-idf | F110: 4 | G110: 4 | H110: 5 | I110: No
A111: Survey 12 | B111: Participant 11 | C111: As a transportation planner, I want to use question answering to quickly find information about transportation regulations, such as vehicle size restrictions and road closures, in order to inform my planning decisions. | D111: Transportation | E111: question answering | F111: 5 | G111: 5 | H111: 3 | I111: No
A112: Survey 12 | B112: Participant 11 | C112: As a plant scientist, I want to use machine learning algorithms to perform word segmentation on plant gene sequences, so that I can identify functional units within the genome and better understand plant physiology and breeding. | D112: Plant Science | E112: word segmentation | F112: 4 | G112: 5 | H112: 4 | I112: No
A113: Survey 17 | B113: Participant 11 | C113: As an information systems analyst, I want to use Gaussian process regression to model the relationships between system performance and various factors such as user behavior and system configurations, so that I can optimize system performance and efficiency. | D113: Information Systems | E113: gaussian process | F113: 4 | G113: 5 | H113: 3 | I113: No
A114: Survey 17 | B114: Participant 11 | C114: As a demographer, I want to use neural networks to analyze demographic data and predict population trends and migration patterns, so that I can better understand population dynamics and inform policy decisions. | D114: Demography | E114: neural network | F114: 5 | G114: 5 | H114: 5 | I114: No
A115: Survey 17 | B115: Participant 11 | C115: As a cardiologist, I want to use tf-idf analysis to identify the most important words and phrases in a corpus of medical literature, so that I can better understand the relationships between cardiac risk factors and their impact on patient outcomes. | D115: Cardiology | E115: tf-idf | F115: 5 | G115: 5 | H115: 5 | I115: No
... A117: Survey 26 | B117: Participant 11 | C117: As an information systems analyst, I want to identify multiword expressions in user search queries to improve search engine functionality. | D117: Information Systems | E117: multiword expressions | F117: 5 | G117: 5 | H117: 5 | I117: No
A118: =A117 -> Survey 26 | B118: Participant 11 | C118: As a neuroscientist, I want to use deep networks to analyze large sets of brain imaging data and identify patterns of neural activity associated with different mental states, so that I can better understand the neural basis of human consciousness. | D118: Biology | E118: deep network | F118: 5 | G118: 3 | H118: 3 | I118: No
A119: =A118 -> Survey 26 | B119: Participant 11 | C119: As an urban planner, I want to use multifactor dimensionality reduction to identify the combination of demographic, socio-economic, and land use factors that contribute to urban growth and development, so that I can make more informed decisions about land use and urban planning. | D119: Urban Studies | E119: multifactor dimensionality reduction | F119: 5 | G119: 5 | H119: 5 | I119: No
...

Sheet Short Statistics
A1: Survey | B1: Responses
A2: Survey 1 | B2: =countif(Results!A:A,A2) -> 14 | F2: 1 | G2: 2 | H2: 3 | I2: 4 | J2: 5
A3: Survey 2 | B3: =countif(Results!A:A,A3) -> 10 | E3: Comprehensibility | F3: =countif(Results!$F:$F,$F$2) -> 11 | G3: =countif(Results!$F:$F,G2) -> 45 | H3: =countif(Results!$F:$F,H2) -> 112 | I3: =countif(Results!$F:$F,I2) -> 315 | J3: =countif(Results!$F:$F,J2) -> 267 | K3: =SUM(F3:J3) -> 750
A4: Survey 3 | B4: =countif(Results!A:A,A4) -> 10 | E4: Actionability | F4: =countif(Results!$G:$G,F$2) -> 11 | G4: =countif(Results!$G:$G,G$2) -> 64 | H4: =countif(Results!$G:$G,H$2) -> 173 | I4: =countif(Results!$G:$G,I$2) -> 307 | J4: =countif(Results!$G:$G,J$2) -> 195 | K4: =SUM(F4:J4) -> 750
A5: Survey 4 | B5: =countif(Results!A:A,A5) -> 10 | E5: Realism | F5: =countif(Results!$H:$H,F$2) -> 30 | G5: =countif(Results!$H:$H,G$2) -> 82 | H5: =countif(Results!$H:$H,H$2) -> 164 | I5: =countif(Results!$H:$H,I$2) -> 257 | J5: =countif(Results!$H:$H,J$2) -> 217 | K5: =SUM(F5:J5) -> 750
A6: Survey 5 | B6: =countif(Results!A:A,A6) -> 13
A7: Survey 6 | B7: =countif(Results!A:A,A7) -> 10
A8: Survey 7 | B8: =countif(Results!A:A,A8) -> 10
A9: Survey 8 | B9: =countif(Results!A:A,A9) -> 14
A10: Survey 9 | B10: =countif(Results!A:A,A10) -> 10
A11: Survey 10 | B11: =countif(Results!A:A,A11) -> 12
A12: Survey 11 | B12: =countif(Results!A:A,A12) -> 10
A13: Survey 12 | B13: =countif(Results!A:A,A13) -> 12
A14: Survey 13 | B14: =countif(Results!A:A,A14) -> 10
A15: Survey 14 | B15: =countif(Results!A:A,A15) -> 10
A16: Survey 15 | B16: =countif(Results!A:A,A16) -> 10
A17: Survey 16 | B17: =countif(Results!A:A,A17) -> 10
... A76: Survey 75 | B76: =countif(Results!A:A,A76) -> 10
